{"nodes": [{"id": "d_qurancaption_src_tauri_python_segment_core_text_matcher_py", "label": "text_matcher.py", "file_type": "code", "source_file": "D:\\QuranCaption\\src-tauri\\python\\segment_core\\text_matcher.py", "source_location": "L1"}, {"id": "segment_core_text_matcher_matchresult", "label": "MatchResult", "file_type": "code", "source_file": "D:\\QuranCaption\\src-tauri\\python\\segment_core\\text_matcher.py", "source_location": "L39"}, {"id": "segment_core_text_matcher_word_similarity", "label": "word_similarity()", "file_type": "code", "source_file": "D:\\QuranCaption\\src-tauri\\python\\segment_core\\text_matcher.py", "source_location": "L50"}, {"id": "segment_core_text_matcher_greedy_match_scores", "label": "greedy_match_scores()", "file_type": "code", "source_file": "D:\\QuranCaption\\src-tauri\\python\\segment_core\\text_matcher.py", "source_location": "L57"}, {"id": "segment_core_text_matcher_match_confidence", "label": "match_confidence()", "file_type": "code", "source_file": "D:\\QuranCaption\\src-tauri\\python\\segment_core\\text_matcher.py", "source_location": "L96"}, {"id": "segment_core_text_matcher_match_segment", "label": "match_segment()", "file_type": "code", "source_file": "D:\\QuranCaption\\src-tauri\\python\\segment_core\\text_matcher.py", "source_location": "L125"}, {"id": "segment_core_text_matcher_has_position_in_range", "label": "_has_position_in_range()", "file_type": "code", "source_file": "D:\\QuranCaption\\src-tauri\\python\\segment_core\\text_matcher.py", "source_location": "L249"}, {"id": "segment_core_text_matcher_pick_anchor_word", "label": "_pick_anchor_word()", "file_type": "code", "source_file": "D:\\QuranCaption\\src-tauri\\python\\segment_core\\text_matcher.py", "source_location": "L255"}, {"id": "segment_core_text_matcher_find_segment_candidates", "label": "_find_segment_candidates()", "file_type": "code", "source_file": "D:\\QuranCaption\\src-tauri\\python\\segment_core\\text_matcher.py", "source_location": "L273"}, {"id": "segment_core_text_matcher_find_global_anchor", "label": "find_global_anchor()", "file_type": "code", "source_file": "D:\\QuranCaption\\src-tauri\\python\\segment_core\\text_matcher.py", "source_location": "L355"}, {"id": "segment_core_text_matcher_textmatcher", "label": "TextMatcher", "file_type": "code", "source_file": "D:\\QuranCaption\\src-tauri\\python\\segment_core\\text_matcher.py", "source_location": "L449"}, {"id": "segment_core_text_matcher_textmatcher_init", "label": ".__init__()", "file_type": "code", "source_file": "D:\\QuranCaption\\src-tauri\\python\\segment_core\\text_matcher.py", "source_location": "L454"}, {"id": "segment_core_text_matcher_textmatcher_reset", "label": ".reset()", "file_type": "code", "source_file": "D:\\QuranCaption\\src-tauri\\python\\segment_core\\text_matcher.py", "source_location": "L460"}, {"id": "segment_core_text_matcher_textmatcher_match_segments", "label": ".match_segments()", "file_type": "code", "source_file": "D:\\QuranCaption\\src-tauri\\python\\segment_core\\text_matcher.py", "source_location": "L466"}, {"id": "segment_core_text_matcher_get_text_matcher", "label": "get_text_matcher()", "file_type": "code", "source_file": "D:\\QuranCaption\\src-tauri\\python\\segment_core\\text_matcher.py", "source_location": "L587"}, {"id": "segment_core_text_matcher_rationale_1", "label": "TextMatcher: Standalone segment-to-Quran text matching.  Matching algorithm:", "file_type": "rationale", "source_file": "D:\\QuranCaption\\src-tauri\\python\\segment_core\\text_matcher.py", "source_location": "L1"}, {"id": "segment_core_text_matcher_rationale_40", "label": "Result of matching a single segment.", "file_type": "rationale", "source_file": "D:\\QuranCaption\\src-tauri\\python\\segment_core\\text_matcher.py", "source_location": "L40"}, {"id": "segment_core_text_matcher_rationale_51", "label": "Return similarity ratio between two words (0-1).", "file_type": "rationale", "source_file": "D:\\QuranCaption\\src-tauri\\python\\segment_core\\text_matcher.py", "source_location": "L51"}, {"id": "segment_core_text_matcher_rationale_58", "label": "Greedy in-order matching: returns (start_pos, span_len, similarity_score) for ma", "file_type": "rationale", "source_file": "D:\\QuranCaption\\src-tauri\\python\\segment_core\\text_matcher.py", "source_location": "L58"}, {"id": "segment_core_text_matcher_rationale_97", "label": "Compute match confidence using weighted F1 over the matched span.", "file_type": "rationale", "source_file": "D:\\QuranCaption\\src-tauri\\python\\segment_core\\text_matcher.py", "source_location": "L97"}, {"id": "segment_core_text_matcher_rationale_131", "label": "Match a single ASR segment to Quran text.", "file_type": "rationale", "source_file": "D:\\QuranCaption\\src-tauri\\python\\segment_core\\text_matcher.py", "source_location": "L131"}, {"id": "segment_core_text_matcher_rationale_250", "label": "Check if any position exists within [start, end].", "file_type": "rationale", "source_file": "D:\\QuranCaption\\src-tauri\\python\\segment_core\\text_matcher.py", "source_location": "L250"}, {"id": "segment_core_text_matcher_rationale_256", "label": "Pick the rarest ASR word to prefilter anchor candidates.", "file_type": "rationale", "source_file": "D:\\QuranCaption\\src-tauri\\python\\segment_core\\text_matcher.py", "source_location": "L256"}, {"id": "segment_core_text_matcher_rationale_278", "label": "Find top-k candidate positions in the Quran for a single ASR segment.", "file_type": "rationale", "source_file": "D:\\QuranCaption\\src-tauri\\python\\segment_core\\text_matcher.py", "source_location": "L278"}, {"id": "segment_core_text_matcher_rationale_359", "label": "Find the best starting position in Quran for a list of segments.", "file_type": "rationale", "source_file": "D:\\QuranCaption\\src-tauri\\python\\segment_core\\text_matcher.py", "source_location": "L359"}, {"id": "segment_core_text_matcher_rationale_450", "label": "Main text matcher for segment-to-Quran alignment.", "file_type": "rationale", "source_file": "D:\\QuranCaption\\src-tauri\\python\\segment_core\\text_matcher.py", "source_location": "L450"}, {"id": "segment_core_text_matcher_rationale_461", "label": "Reset matcher state for new audio.", "file_type": "rationale", "source_file": "D:\\QuranCaption\\src-tauri\\python\\segment_core\\text_matcher.py", "source_location": "L461"}, {"id": "segment_core_text_matcher_rationale_467", "label": "Match a list of transcribed segments to Quran text.", "file_type": "rationale", "source_file": "D:\\QuranCaption\\src-tauri\\python\\segment_core\\text_matcher.py", "source_location": "L467"}, {"id": "segment_core_text_matcher_rationale_588", "label": "Get or create the global TextMatcher singleton.", "file_type": "rationale", "source_file": "D:\\QuranCaption\\src-tauri\\python\\segment_core\\text_matcher.py", "source_location": "L588"}], "edges": [{"source": "d_qurancaption_src_tauri_python_segment_core_text_matcher_py", "target": "bisect", "relation": "imports_from", "confidence": "EXTRACTED", "source_file": "D:\\QuranCaption\\src-tauri\\python\\segment_core\\text_matcher.py", "source_location": "L12", "weight": 1.0}, {"source": "d_qurancaption_src_tauri_python_segment_core_text_matcher_py", "target": "dataclasses", "relation": "imports_from", "confidence": "EXTRACTED", "source_file": "D:\\QuranCaption\\src-tauri\\python\\segment_core\\text_matcher.py", "source_location": "L13", "weight": 1.0}, {"source": "d_qurancaption_src_tauri_python_segment_core_text_matcher_py", "target": "difflib", "relation": "imports_from", "confidence": "EXTRACTED", "source_file": "D:\\QuranCaption\\src-tauri\\python\\segment_core\\text_matcher.py", "source_location": "L14", "weight": 1.0}, {"source": "d_qurancaption_src_tauri_python_segment_core_text_matcher_py", "target": "typing", "relation": "imports_from", "confidence": "EXTRACTED", "source_file": "D:\\QuranCaption\\src-tauri\\python\\segment_core\\text_matcher.py", "source_location": "L15", "weight": 1.0}, {"source": "d_qurancaption_src_tauri_python_segment_core_text_matcher_py", "target": "d_qurancaption_src_tauri_python_segment_core_config_py", "relation": "imports_from", "confidence": "EXTRACTED", "source_file": "D:\\QuranCaption\\src-tauri\\python\\segment_core\\text_matcher.py", "source_location": "L17", "weight": 1.0}, {"source": "d_qurancaption_src_tauri_python_segment_core_text_matcher_py", "target": "d_qurancaption_src_tauri_python_segment_core_quran_index_py", "relation": "imports_from", "confidence": "EXTRACTED", "source_file": "D:\\QuranCaption\\src-tauri\\python\\segment_core\\text_matcher.py", "source_location": "L32", "weight": 1.0}, {"source": "d_qurancaption_src_tauri_python_segment_core_text_matcher_py", "target": "d_qurancaption_src_tauri_python_segment_core_text_preprocessor_py", "relation": "imports_from", "confidence": "EXTRACTED", "source_file": "D:\\QuranCaption\\src-tauri\\python\\segment_core\\text_matcher.py", "source_location": "L33", "weight": 1.0}, {"source": "d_qurancaption_src_tauri_python_segment_core_text_matcher_py", "target": "d_qurancaption_src_tauri_python_segment_core_special_segments_py", "relation": "imports_from", "confidence": "EXTRACTED", "source_file": "D:\\QuranCaption\\src-tauri\\python\\segment_core\\text_matcher.py", "source_location": "L34", "weight": 1.0}, {"source": "d_qurancaption_src_tauri_python_segment_core_text_matcher_py", "target": "segment_core_text_matcher_matchresult", "relation": "contains", "confidence": "EXTRACTED", "source_file": "D:\\QuranCaption\\src-tauri\\python\\segment_core\\text_matcher.py", "source_location": "L39", "weight": 1.0}, {"source": "d_qurancaption_src_tauri_python_segment_core_text_matcher_py", "target": "segment_core_text_matcher_word_similarity", "relation": "contains", "confidence": "EXTRACTED", "source_file": "D:\\QuranCaption\\src-tauri\\python\\segment_core\\text_matcher.py", "source_location": "L50", "weight": 1.0}, {"source": "d_qurancaption_src_tauri_python_segment_core_text_matcher_py", "target": "segment_core_text_matcher_greedy_match_scores", "relation": "contains", "confidence": "EXTRACTED", "source_file": "D:\\QuranCaption\\src-tauri\\python\\segment_core\\text_matcher.py", "source_location": "L57", "weight": 1.0}, {"source": "d_qurancaption_src_tauri_python_segment_core_text_matcher_py", "target": "segment_core_text_matcher_match_confidence", "relation": "contains", "confidence": "EXTRACTED", "source_file": "D:\\QuranCaption\\src-tauri\\python\\segment_core\\text_matcher.py", "source_location": "L96", "weight": 1.0}, {"source": "d_qurancaption_src_tauri_python_segment_core_text_matcher_py", "target": "segment_core_text_matcher_match_segment", "relation": "contains", "confidence": "EXTRACTED", "source_file": "D:\\QuranCaption\\src-tauri\\python\\segment_core\\text_matcher.py", "source_location": "L125", "weight": 1.0}, {"source": "d_qurancaption_src_tauri_python_segment_core_text_matcher_py", "target": "segment_core_text_matcher_has_position_in_range", "relation": "contains", "confidence": "EXTRACTED", "source_file": "D:\\QuranCaption\\src-tauri\\python\\segment_core\\text_matcher.py", "source_location": "L249", "weight": 1.0}, {"source": "d_qurancaption_src_tauri_python_segment_core_text_matcher_py", "target": "segment_core_text_matcher_pick_anchor_word", "relation": "contains", "confidence": "EXTRACTED", "source_file": "D:\\QuranCaption\\src-tauri\\python\\segment_core\\text_matcher.py", "source_location": "L255", "weight": 1.0}, {"source": "d_qurancaption_src_tauri_python_segment_core_text_matcher_py", "target": "segment_core_text_matcher_find_segment_candidates", "relation": "contains", "confidence": "EXTRACTED", "source_file": "D:\\QuranCaption\\src-tauri\\python\\segment_core\\text_matcher.py", "source_location": "L273", "weight": 1.0}, {"source": "d_qurancaption_src_tauri_python_segment_core_text_matcher_py", "target": "segment_core_text_matcher_find_global_anchor", "relation": "contains", "confidence": "EXTRACTED", "source_file": "D:\\QuranCaption\\src-tauri\\python\\segment_core\\text_matcher.py", "source_location": "L355", "weight": 1.0}, {"source": "d_qurancaption_src_tauri_python_segment_core_text_matcher_py", "target": "segment_core_text_matcher_textmatcher", "relation": "contains", "confidence": "EXTRACTED", "source_file": "D:\\QuranCaption\\src-tauri\\python\\segment_core\\text_matcher.py", "source_location": "L449", "weight": 1.0}, {"source": "segment_core_text_matcher_textmatcher", "target": "segment_core_text_matcher_textmatcher_init", "relation": "method", "confidence": "EXTRACTED", "source_file": "D:\\QuranCaption\\src-tauri\\python\\segment_core\\text_matcher.py", "source_location": "L454", "weight": 1.0}, {"source": "segment_core_text_matcher_textmatcher", "target": "segment_core_text_matcher_textmatcher_reset", "relation": "method", "confidence": "EXTRACTED", "source_file": "D:\\QuranCaption\\src-tauri\\python\\segment_core\\text_matcher.py", "source_location": "L460", "weight": 1.0}, {"source": "segment_core_text_matcher_textmatcher", "target": "segment_core_text_matcher_textmatcher_match_segments", "relation": "method", "confidence": "EXTRACTED", "source_file": "D:\\QuranCaption\\src-tauri\\python\\segment_core\\text_matcher.py", "source_location": "L466", "weight": 1.0}, {"source": "d_qurancaption_src_tauri_python_segment_core_text_matcher_py", "target": "segment_core_text_matcher_get_text_matcher", "relation": "contains", "confidence": "EXTRACTED", "source_file": "D:\\QuranCaption\\src-tauri\\python\\segment_core\\text_matcher.py", "source_location": "L587", "weight": 1.0}, {"source": "segment_core_text_matcher_greedy_match_scores", "target": "segment_core_text_matcher_word_similarity", "relation": "calls", "confidence": "EXTRACTED", "source_file": "D:\\QuranCaption\\src-tauri\\python\\segment_core\\text_matcher.py", "source_location": "L74", "weight": 1.0}, {"source": "segment_core_text_matcher_match_confidence", "target": "segment_core_text_matcher_greedy_match_scores", "relation": "calls", "confidence": "EXTRACTED", "source_file": "D:\\QuranCaption\\src-tauri\\python\\segment_core\\text_matcher.py", "source_location": "L98", "weight": 1.0}, {"source": "segment_core_text_matcher_match_segment", "target": "segment_core_text_matcher_matchresult", "relation": "calls", "confidence": "EXTRACTED", "source_file": "D:\\QuranCaption\\src-tauri\\python\\segment_core\\text_matcher.py", "source_location": "L145", "weight": 1.0}, {"source": "segment_core_text_matcher_match_segment", "target": "segment_core_text_matcher_match_confidence", "relation": "calls", "confidence": "EXTRACTED", "source_file": "D:\\QuranCaption\\src-tauri\\python\\segment_core\\text_matcher.py", "source_location": "L178", "weight": 1.0}, {"source": "segment_core_text_matcher_find_segment_candidates", "target": "segment_core_text_matcher_pick_anchor_word", "relation": "calls", "confidence": "EXTRACTED", "source_file": "D:\\QuranCaption\\src-tauri\\python\\segment_core\\text_matcher.py", "source_location": "L289", "weight": 1.0}, {"source": "segment_core_text_matcher_find_segment_candidates", "target": "segment_core_text_matcher_has_position_in_range", "relation": "calls", "confidence": "EXTRACTED", "source_file": "D:\\QuranCaption\\src-tauri\\python\\segment_core\\text_matcher.py", "source_location": "L307", "weight": 1.0}, {"source": "segment_core_text_matcher_find_segment_candidates", "target": "segment_core_text_matcher_match_confidence", "relation": "calls", "confidence": "EXTRACTED", "source_file": "D:\\QuranCaption\\src-tauri\\python\\segment_core\\text_matcher.py", "source_location": "L327", "weight": 1.0}, {"source": "segment_core_text_matcher_find_global_anchor", "target": "segment_core_text_matcher_find_segment_candidates", "relation": "calls", "confidence": "EXTRACTED", "source_file": "D:\\QuranCaption\\src-tauri\\python\\segment_core\\text_matcher.py", "source_location": "L377", "weight": 1.0}, {"source": "segment_core_text_matcher_textmatcher_match_segments", "target": "segment_core_text_matcher_textmatcher_reset", "relation": "calls", "confidence": "EXTRACTED", "source_file": "D:\\QuranCaption\\src-tauri\\python\\segment_core\\text_matcher.py", "source_location": "L470", "weight": 1.0}, {"source": "segment_core_text_matcher_textmatcher_match_segments", "target": "segment_core_text_matcher_find_global_anchor", "relation": "calls", "confidence": "EXTRACTED", "source_file": "D:\\QuranCaption\\src-tauri\\python\\segment_core\\text_matcher.py", "source_location": "L521", "weight": 1.0}, {"source": "segment_core_text_matcher_textmatcher_match_segments", "target": "segment_core_text_matcher_matchresult", "relation": "calls", "confidence": "EXTRACTED", "source_file": "D:\\QuranCaption\\src-tauri\\python\\segment_core\\text_matcher.py", "source_location": "L532", "weight": 1.0}, {"source": "segment_core_text_matcher_textmatcher_match_segments", "target": "segment_core_text_matcher_match_segment", "relation": "calls", "confidence": "EXTRACTED", "source_file": "D:\\QuranCaption\\src-tauri\\python\\segment_core\\text_matcher.py", "source_location": "L535", "weight": 1.0}, {"source": "segment_core_text_matcher_get_text_matcher", "target": "segment_core_text_matcher_textmatcher", "relation": "calls", "confidence": "EXTRACTED", "source_file": "D:\\QuranCaption\\src-tauri\\python\\segment_core\\text_matcher.py", "source_location": "L591", "weight": 1.0}, {"source": "segment_core_text_matcher_rationale_1", "target": "d_qurancaption_src_tauri_python_segment_core_text_matcher_py", "relation": "rationale_for", "confidence": "EXTRACTED", "source_file": "D:\\QuranCaption\\src-tauri\\python\\segment_core\\text_matcher.py", "source_location": "L1", "weight": 1.0}, {"source": "segment_core_text_matcher_rationale_40", "target": "segment_core_text_matcher_matchresult", "relation": "rationale_for", "confidence": "EXTRACTED", "source_file": "D:\\QuranCaption\\src-tauri\\python\\segment_core\\text_matcher.py", "source_location": "L40", "weight": 1.0}, {"source": "segment_core_text_matcher_rationale_51", "target": "segment_core_text_matcher_word_similarity", "relation": "rationale_for", "confidence": "EXTRACTED", "source_file": "D:\\QuranCaption\\src-tauri\\python\\segment_core\\text_matcher.py", "source_location": "L51", "weight": 1.0}, {"source": "segment_core_text_matcher_rationale_58", "target": "segment_core_text_matcher_greedy_match_scores", "relation": "rationale_for", "confidence": "EXTRACTED", "source_file": "D:\\QuranCaption\\src-tauri\\python\\segment_core\\text_matcher.py", "source_location": "L58", "weight": 1.0}, {"source": "segment_core_text_matcher_rationale_97", "target": "segment_core_text_matcher_match_confidence", "relation": "rationale_for", "confidence": "EXTRACTED", "source_file": "D:\\QuranCaption\\src-tauri\\python\\segment_core\\text_matcher.py", "source_location": "L97", "weight": 1.0}, {"source": "segment_core_text_matcher_rationale_131", "target": "segment_core_text_matcher_match_segment", "relation": "rationale_for", "confidence": "EXTRACTED", "source_file": "D:\\QuranCaption\\src-tauri\\python\\segment_core\\text_matcher.py", "source_location": "L131", "weight": 1.0}, {"source": "segment_core_text_matcher_rationale_250", "target": "segment_core_text_matcher_has_position_in_range", "relation": "rationale_for", "confidence": "EXTRACTED", "source_file": "D:\\QuranCaption\\src-tauri\\python\\segment_core\\text_matcher.py", "source_location": "L250", "weight": 1.0}, {"source": "segment_core_text_matcher_rationale_256", "target": "segment_core_text_matcher_pick_anchor_word", "relation": "rationale_for", "confidence": "EXTRACTED", "source_file": "D:\\QuranCaption\\src-tauri\\python\\segment_core\\text_matcher.py", "source_location": "L256", "weight": 1.0}, {"source": "segment_core_text_matcher_rationale_278", "target": "segment_core_text_matcher_find_segment_candidates", "relation": "rationale_for", "confidence": "EXTRACTED", "source_file": "D:\\QuranCaption\\src-tauri\\python\\segment_core\\text_matcher.py", "source_location": "L278", "weight": 1.0}, {"source": "segment_core_text_matcher_rationale_359", "target": "segment_core_text_matcher_find_global_anchor", "relation": "rationale_for", "confidence": "EXTRACTED", "source_file": "D:\\QuranCaption\\src-tauri\\python\\segment_core\\text_matcher.py", "source_location": "L359", "weight": 1.0}, {"source": "segment_core_text_matcher_rationale_450", "target": "segment_core_text_matcher_textmatcher", "relation": "rationale_for", "confidence": "EXTRACTED", "source_file": "D:\\QuranCaption\\src-tauri\\python\\segment_core\\text_matcher.py", "source_location": "L450", "weight": 1.0}, {"source": "segment_core_text_matcher_rationale_461", "target": "segment_core_text_matcher_textmatcher_reset", "relation": "rationale_for", "confidence": "EXTRACTED", "source_file": "D:\\QuranCaption\\src-tauri\\python\\segment_core\\text_matcher.py", "source_location": "L461", "weight": 1.0}, {"source": "segment_core_text_matcher_rationale_467", "target": "segment_core_text_matcher_textmatcher_match_segments", "relation": "rationale_for", "confidence": "EXTRACTED", "source_file": "D:\\QuranCaption\\src-tauri\\python\\segment_core\\text_matcher.py", "source_location": "L467", "weight": 1.0}, {"source": "segment_core_text_matcher_rationale_588", "target": "segment_core_text_matcher_get_text_matcher", "relation": "rationale_for", "confidence": "EXTRACTED", "source_file": "D:\\QuranCaption\\src-tauri\\python\\segment_core\\text_matcher.py", "source_location": "L588", "weight": 1.0}], "raw_calls": [{"caller_nid": "segment_core_text_matcher_word_similarity", "callee": "ratio", "is_member_call": true, "source_file": "D:\\QuranCaption\\src-tauri\\python\\segment_core\\text_matcher.py", "source_location": "L54"}, {"caller_nid": "segment_core_text_matcher_word_similarity", "callee": "SequenceMatcher", "is_member_call": false, "source_file": "D:\\QuranCaption\\src-tauri\\python\\segment_core\\text_matcher.py", "source_location": "L54"}, {"caller_nid": "segment_core_text_matcher_greedy_match_scores", "callee": "len", "is_member_call": false, "source_file": "D:\\QuranCaption\\src-tauri\\python\\segment_core\\text_matcher.py", "source_location": "L66"}, {"caller_nid": "segment_core_text_matcher_greedy_match_scores", "callee": "min", "is_member_call": false, "source_file": "D:\\QuranCaption\\src-tauri\\python\\segment_core\\text_matcher.py", "source_location": "L71"}, {"caller_nid": "segment_core_text_matcher_greedy_match_scores", "callee": "append", "is_member_call": true, "source_file": "D:\\QuranCaption\\src-tauri\\python\\segment_core\\text_matcher.py", "source_location": "L76"}, {"caller_nid": "segment_core_text_matcher_greedy_match_scores", "callee": "append", "is_member_call": true, "source_file": "D:\\QuranCaption\\src-tauri\\python\\segment_core\\text_matcher.py", "source_location": "L84"}, {"caller_nid": "segment_core_text_matcher_match_confidence", "callee": "sum", "is_member_call": false, "source_file": "D:\\QuranCaption\\src-tauri\\python\\segment_core\\text_matcher.py", "source_location": "L102"}, {"caller_nid": "segment_core_text_matcher_match_confidence", "callee": "max", "is_member_call": false, "source_file": "D:\\QuranCaption\\src-tauri\\python\\segment_core\\text_matcher.py", "source_location": "L104"}, {"caller_nid": "segment_core_text_matcher_match_confidence", "callee": "len", "is_member_call": false, "source_file": "D:\\QuranCaption\\src-tauri\\python\\segment_core\\text_matcher.py", "source_location": "L108"}, {"caller_nid": "segment_core_text_matcher_match_segment", "callee": "perf_counter", "is_member_call": true, "source_file": "D:\\QuranCaption\\src-tauri\\python\\segment_core\\text_matcher.py", "source_location": "L138"}, {"caller_nid": "segment_core_text_matcher_match_segment", "callee": "normalize_arabic", "is_member_call": false, "source_file": "D:\\QuranCaption\\src-tauri\\python\\segment_core\\text_matcher.py", "source_location": "L139"}, {"caller_nid": "segment_core_text_matcher_match_segment", "callee": "split_words", "is_member_call": false, "source_file": "D:\\QuranCaption\\src-tauri\\python\\segment_core\\text_matcher.py", "source_location": "L140"}, {"caller_nid": "segment_core_text_matcher_match_segment", "callee": "len", "is_member_call": false, "source_file": "D:\\QuranCaption\\src-tauri\\python\\segment_core\\text_matcher.py", "source_location": "L141"}, {"caller_nid": "segment_core_text_matcher_match_segment", "callee": "perf_counter", "is_member_call": true, "source_file": "D:\\QuranCaption\\src-tauri\\python\\segment_core\\text_matcher.py", "source_location": "L142"}, {"caller_nid": "segment_core_text_matcher_match_segment", "callee": "perf_counter", "is_member_call": true, "source_file": "D:\\QuranCaption\\src-tauri\\python\\segment_core\\text_matcher.py", "source_location": "L148"}, {"caller_nid": "segment_core_text_matcher_match_segment", "callee": "max", "is_member_call": false, "source_file": "D:\\QuranCaption\\src-tauri\\python\\segment_core\\text_matcher.py", "source_location": "L154"}, {"caller_nid": "segment_core_text_matcher_match_segment", "callee": "min", "is_member_call": false, "source_file": "D:\\QuranCaption\\src-tauri\\python\\segment_core\\text_matcher.py", "source_location": "L154"}, {"caller_nid": "segment_core_text_matcher_match_segment", "callee": "perf_counter", "is_member_call": true, "source_file": "D:\\QuranCaption\\src-tauri\\python\\segment_core\\text_matcher.py", "source_location": "L155"}, {"caller_nid": "segment_core_text_matcher_match_segment", "callee": "perf_counter", "is_member_call": true, "source_file": "D:\\QuranCaption\\src-tauri\\python\\segment_core\\text_matcher.py", "source_location": "L160"}, {"caller_nid": "segment_core_text_matcher_match_segment", "callee": "range", "is_member_call": false, "source_file": "D:\\QuranCaption\\src-tauri\\python\\segment_core\\text_matcher.py", "source_location": "L163"}, {"caller_nid": "segment_core_text_matcher_match_segment", "callee": "range", "is_member_call": false, "source_file": "D:\\QuranCaption\\src-tauri\\python\\segment_core\\text_matcher.py", "source_location": "L168"}, {"caller_nid": "segment_core_text_matcher_match_segment", "callee": "max", "is_member_call": false, "source_file": "D:\\QuranCaption\\src-tauri\\python\\segment_core\\text_matcher.py", "source_location": "L168"}, {"caller_nid": "segment_core_text_matcher_match_segment", "callee": "min", "is_member_call": false, "source_file": "D:\\QuranCaption\\src-tauri\\python\\segment_core\\text_matcher.py", "source_location": "L169"}, {"caller_nid": "segment_core_text_matcher_match_segment", "callee": "get_slice", "is_member_call": true, "source_file": "D:\\QuranCaption\\src-tauri\\python\\segment_core\\text_matcher.py", "source_location": "L173"}, {"caller_nid": "segment_core_text_matcher_match_segment", "callee": "perf_counter", "is_member_call": true, "source_file": "D:\\QuranCaption\\src-tauri\\python\\segment_core\\text_matcher.py", "source_location": "L177"}, {"caller_nid": "segment_core_text_matcher_match_segment", "callee": "perf_counter", "is_member_call": true, "source_file": "D:\\QuranCaption\\src-tauri\\python\\segment_core\\text_matcher.py", "source_location": "L179"}, {"caller_nid": "segment_core_text_matcher_match_segment", "callee": "get", "is_member_call": true, "source_file": "D:\\QuranCaption\\src-tauri\\python\\segment_core\\text_matcher.py", "source_location": "L197"}, {"caller_nid": "segment_core_text_matcher_match_segment", "callee": "perf_counter", "is_member_call": true, "source_file": "D:\\QuranCaption\\src-tauri\\python\\segment_core\\text_matcher.py", "source_location": "L201"}, {"caller_nid": "segment_core_text_matcher_match_segment", "callee": "len", "is_member_call": false, "source_file": "D:\\QuranCaption\\src-tauri\\python\\segment_core\\text_matcher.py", "source_location": "L203"}, {"caller_nid": "segment_core_text_matcher_match_segment", "callee": "perf_counter", "is_member_call": true, "source_file": "D:\\QuranCaption\\src-tauri\\python\\segment_core\\text_matcher.py", "source_location": "L209"}, {"caller_nid": "segment_core_text_matcher_match_segment", "callee": "list", "is_member_call": false, "source_file": "D:\\QuranCaption\\src-tauri\\python\\segment_core\\text_matcher.py", "source_location": "L210"}, {"caller_nid": "segment_core_text_matcher_match_segment", "callee": "values", "is_member_call": true, "source_file": "D:\\QuranCaption\\src-tauri\\python\\segment_core\\text_matcher.py", "source_location": "L210"}, {"caller_nid": "segment_core_text_matcher_match_segment", "callee": "sort", "is_member_call": true, "source_file": "D:\\QuranCaption\\src-tauri\\python\\segment_core\\text_matcher.py", "source_location": "L211"}, {"caller_nid": "segment_core_text_matcher_match_segment", "callee": "abs", "is_member_call": false, "source_file": "D:\\QuranCaption\\src-tauri\\python\\segment_core\\text_matcher.py", "source_location": "L215"}, {"caller_nid": "segment_core_text_matcher_match_segment", "callee": "perf_counter", "is_member_call": true, "source_file": "D:\\QuranCaption\\src-tauri\\python\\segment_core\\text_matcher.py", "source_location": "L220"}, {"caller_nid": "segment_core_text_matcher_match_segment", "callee": "perf_counter", "is_member_call": true, "source_file": "D:\\QuranCaption\\src-tauri\\python\\segment_core\\text_matcher.py", "source_location": "L223"}, {"caller_nid": "segment_core_text_matcher_match_segment", "callee": "to_ref", "is_member_call": true, "source_file": "D:\\QuranCaption\\src-tauri\\python\\segment_core\\text_matcher.py", "source_location": "L225"}, {"caller_nid": "segment_core_text_matcher_match_segment", "callee": "get_original_text", "is_member_call": true, "source_file": "D:\\QuranCaption\\src-tauri\\python\\segment_core\\text_matcher.py", "source_location": "L226"}, {"caller_nid": "segment_core_text_matcher_match_segment", "callee": "perf_counter", "is_member_call": true, "source_file": "D:\\QuranCaption\\src-tauri\\python\\segment_core\\text_matcher.py", "source_location": "L228"}, {"caller_nid": "segment_core_text_matcher_match_segment", "callee": "get_slice", "is_member_call": true, "source_file": "D:\\QuranCaption\\src-tauri\\python\\segment_core\\text_matcher.py", "source_location": "L230"}, {"caller_nid": "segment_core_text_matcher_match_segment", "callee": "perf_counter", "is_member_call": true, "source_file": "D:\\QuranCaption\\src-tauri\\python\\segment_core\\text_matcher.py", "source_location": "L242"}, {"caller_nid": "segment_core_text_matcher_has_position_in_range", "callee": "bisect_left", "is_member_call": false, "source_file": "D:\\QuranCaption\\src-tauri\\python\\segment_core\\text_matcher.py", "source_location": "L251"}, {"caller_nid": "segment_core_text_matcher_has_position_in_range", "callee": "len", "is_member_call": false, "source_file": "D:\\QuranCaption\\src-tauri\\python\\segment_core\\text_matcher.py", "source_location": "L252"}, {"caller_nid": "segment_core_text_matcher_pick_anchor_word", "callee": "enumerate", "is_member_call": false, "source_file": "D:\\QuranCaption\\src-tauri\\python\\segment_core\\text_matcher.py", "source_location": "L261"}, {"caller_nid": "segment_core_text_matcher_pick_anchor_word", "callee": "get_positions", "is_member_call": true, "source_file": "D:\\QuranCaption\\src-tauri\\python\\segment_core\\text_matcher.py", "source_location": "L262"}, {"caller_nid": "segment_core_text_matcher_pick_anchor_word", "callee": "len", "is_member_call": false, "source_file": "D:\\QuranCaption\\src-tauri\\python\\segment_core\\text_matcher.py", "source_location": "L265"}, {"caller_nid": "segment_core_text_matcher_pick_anchor_word", "callee": "len", "is_member_call": false, "source_file": "D:\\QuranCaption\\src-tauri\\python\\segment_core\\text_matcher.py", "source_location": "L265"}, {"caller_nid": "segment_core_text_matcher_find_segment_candidates", "callee": "normalize_arabic", "is_member_call": false, "source_file": "D:\\QuranCaption\\src-tauri\\python\\segment_core\\text_matcher.py", "source_location": "L279"}, {"caller_nid": "segment_core_text_matcher_find_segment_candidates", "callee": "split_words", "is_member_call": false, "source_file": "D:\\QuranCaption\\src-tauri\\python\\segment_core\\text_matcher.py", "source_location": "L280"}, {"caller_nid": "segment_core_text_matcher_find_segment_candidates", "callee": "len", "is_member_call": false, "source_file": "D:\\QuranCaption\\src-tauri\\python\\segment_core\\text_matcher.py", "source_location": "L281"}, {"caller_nid": "segment_core_text_matcher_find_segment_candidates", "callee": "max", "is_member_call": false, "source_file": "D:\\QuranCaption\\src-tauri\\python\\segment_core\\text_matcher.py", "source_location": "L286"}, {"caller_nid": "segment_core_text_matcher_find_segment_candidates", "callee": "get_positions", "is_member_call": true, "source_file": "D:\\QuranCaption\\src-tauri\\python\\segment_core\\text_matcher.py", "source_location": "L293"}, {"caller_nid": "segment_core_text_matcher_find_segment_candidates", "callee": "set", "is_member_call": false, "source_file": "D:\\QuranCaption\\src-tauri\\python\\segment_core\\text_matcher.py", "source_location": "L294"}, {"caller_nid": "segment_core_text_matcher_find_segment_candidates", "callee": "range", "is_member_call": false, "source_file": "D:\\QuranCaption\\src-tauri\\python\\segment_core\\text_matcher.py", "source_location": "L298"}, {"caller_nid": "segment_core_text_matcher_find_segment_candidates", "callee": "min", "is_member_call": false, "source_file": "D:\\QuranCaption\\src-tauri\\python\\segment_core\\text_matcher.py", "source_location": "L306"}, {"caller_nid": "segment_core_text_matcher_find_segment_candidates", "callee": "add", "is_member_call": true, "source_file": "D:\\QuranCaption\\src-tauri\\python\\segment_core\\text_matcher.py", "source_location": "L310"}, {"caller_nid": "segment_core_text_matcher_find_segment_candidates", "callee": "range", "is_member_call": false, "source_file": "D:\\QuranCaption\\src-tauri\\python\\segment_core\\text_matcher.py", "source_location": "L318"}, {"caller_nid": "segment_core_text_matcher_find_segment_candidates", "callee": "min", "is_member_call": false, "source_file": "D:\\QuranCaption\\src-tauri\\python\\segment_core\\text_matcher.py", "source_location": "L319"}, {"caller_nid": "segment_core_text_matcher_find_segment_candidates", "callee": "get_slice", "is_member_call": true, "source_file": "D:\\QuranCaption\\src-tauri\\python\\segment_core\\text_matcher.py", "source_location": "L323"}, {"caller_nid": "segment_core_text_matcher_find_segment_candidates", "callee": "get_word", "is_member_call": true, "source_file": "D:\\QuranCaption\\src-tauri\\python\\segment_core\\text_matcher.py", "source_location": "L333"}, {"caller_nid": "segment_core_text_matcher_find_segment_candidates", "callee": "get", "is_member_call": true, "source_file": "D:\\QuranCaption\\src-tauri\\python\\segment_core\\text_matcher.py", "source_location": "L346"}, {"caller_nid": "segment_core_text_matcher_find_segment_candidates", "callee": "list", "is_member_call": false, "source_file": "D:\\QuranCaption\\src-tauri\\python\\segment_core\\text_matcher.py", "source_location": "L350"}, {"caller_nid": "segment_core_text_matcher_find_segment_candidates", "callee": "values", "is_member_call": true, "source_file": "D:\\QuranCaption\\src-tauri\\python\\segment_core\\text_matcher.py", "source_location": "L350"}, {"caller_nid": "segment_core_text_matcher_find_segment_candidates", "callee": "sort", "is_member_call": true, "source_file": "D:\\QuranCaption\\src-tauri\\python\\segment_core\\text_matcher.py", "source_location": "L351"}, {"caller_nid": "segment_core_text_matcher_find_global_anchor", "callee": "strip", "is_member_call": true, "source_file": "D:\\QuranCaption\\src-tauri\\python\\segment_core\\text_matcher.py", "source_location": "L363"}, {"caller_nid": "segment_core_text_matcher_find_global_anchor", "callee": "len", "is_member_call": false, "source_file": "D:\\QuranCaption\\src-tauri\\python\\segment_core\\text_matcher.py", "source_location": "L366"}, {"caller_nid": "segment_core_text_matcher_find_global_anchor", "callee": "split_words", "is_member_call": false, "source_file": "D:\\QuranCaption\\src-tauri\\python\\segment_core\\text_matcher.py", "source_location": "L366"}, {"caller_nid": "segment_core_text_matcher_find_global_anchor", "callee": "normalize_arabic", "is_member_call": false, "source_file": "D:\\QuranCaption\\src-tauri\\python\\segment_core\\text_matcher.py", "source_location": "L366"}, {"caller_nid": "segment_core_text_matcher_find_global_anchor", "callee": "append", "is_member_call": true, "source_file": "D:\\QuranCaption\\src-tauri\\python\\segment_core\\text_matcher.py", "source_location": "L367"}, {"caller_nid": "segment_core_text_matcher_find_global_anchor", "callee": "enumerate", "is_member_call": false, "source_file": "D:\\QuranCaption\\src-tauri\\python\\segment_core\\text_matcher.py", "source_location": "L376"}, {"caller_nid": "segment_core_text_matcher_find_global_anchor", "callee": "append", "is_member_call": true, "source_file": "D:\\QuranCaption\\src-tauri\\python\\segment_core\\text_matcher.py", "source_location": "L378"}, {"caller_nid": "segment_core_text_matcher_find_global_anchor", "callee": "any", "is_member_call": false, "source_file": "D:\\QuranCaption\\src-tauri\\python\\segment_core\\text_matcher.py", "source_location": "L380"}, {"caller_nid": "segment_core_text_matcher_find_global_anchor", "callee": "print", "is_member_call": false, "source_file": "D:\\QuranCaption\\src-tauri\\python\\segment_core\\text_matcher.py", "source_location": "L381"}, {"caller_nid": "segment_core_text_matcher_find_global_anchor", "callee": "enumerate", "is_member_call": false, "source_file": "D:\\QuranCaption\\src-tauri\\python\\segment_core\\text_matcher.py", "source_location": "L385"}, {"caller_nid": "segment_core_text_matcher_find_global_anchor", "callee": "len", "is_member_call": false, "source_file": "D:\\QuranCaption\\src-tauri\\python\\segment_core\\text_matcher.py", "source_location": "L387"}, {"caller_nid": "segment_core_text_matcher_find_global_anchor", "callee": "print", "is_member_call": false, "source_file": "D:\\QuranCaption\\src-tauri\\python\\segment_core\\text_matcher.py", "source_location": "L390"}, {"caller_nid": "segment_core_text_matcher_find_global_anchor", "callee": "range", "is_member_call": false, "source_file": "D:\\QuranCaption\\src-tauri\\python\\segment_core\\text_matcher.py", "source_location": "L409"}, {"caller_nid": "segment_core_text_matcher_find_global_anchor", "callee": "len", "is_member_call": false, "source_file": "D:\\QuranCaption\\src-tauri\\python\\segment_core\\text_matcher.py", "source_location": "L409"}, {"caller_nid": "segment_core_text_matcher_find_global_anchor", "callee": "abs", "is_member_call": false, "source_file": "D:\\QuranCaption\\src-tauri\\python\\segment_core\\text_matcher.py", "source_location": "L421"}, {"caller_nid": "segment_core_text_matcher_find_global_anchor", "callee": "max", "is_member_call": false, "source_file": "D:\\QuranCaption\\src-tauri\\python\\segment_core\\text_matcher.py", "source_location": "L421"}, {"caller_nid": "segment_core_text_matcher_find_global_anchor", "callee": "max", "is_member_call": false, "source_file": "D:\\QuranCaption\\src-tauri\\python\\segment_core\\text_matcher.py", "source_location": "L433"}, {"caller_nid": "segment_core_text_matcher_find_global_anchor", "callee": "print", "is_member_call": false, "source_file": "D:\\QuranCaption\\src-tauri\\python\\segment_core\\text_matcher.py", "source_location": "L442"}, {"caller_nid": "segment_core_text_matcher_textmatcher_init", "callee": "get_quran_index", "is_member_call": false, "source_file": "D:\\QuranCaption\\src-tauri\\python\\segment_core\\text_matcher.py", "source_location": "L455"}, {"caller_nid": "segment_core_text_matcher_textmatcher_match_segments", "callee": "time", "is_member_call": true, "source_file": "D:\\QuranCaption\\src-tauri\\python\\segment_core\\text_matcher.py", "source_location": "L471"}, {"caller_nid": "segment_core_text_matcher_textmatcher_match_segments", "callee": "len", "is_member_call": false, "source_file": "D:\\QuranCaption\\src-tauri\\python\\segment_core\\text_matcher.py", "source_location": "L472"}, {"caller_nid": "segment_core_text_matcher_textmatcher_match_segments", "callee": "set", "is_member_call": false, "source_file": "D:\\QuranCaption\\src-tauri\\python\\segment_core\\text_matcher.py", "source_location": "L479"}, {"caller_nid": "segment_core_text_matcher_textmatcher_match_segments", "callee": "strip", "is_member_call": true, "source_file": "D:\\QuranCaption\\src-tauri\\python\\segment_core\\text_matcher.py", "source_location": "L494"}, {"caller_nid": "segment_core_text_matcher_textmatcher_match_segments", "callee": "get_special_scores", "is_member_call": false, "source_file": "D:\\QuranCaption\\src-tauri\\python\\segment_core\\text_matcher.py", "source_location": "L495"}, {"caller_nid": "segment_core_text_matcher_textmatcher_match_segments", "callee": "get", "is_member_call": true, "source_file": "D:\\QuranCaption\\src-tauri\\python\\segment_core\\text_matcher.py", "source_location": "L496"}, {"caller_nid": "segment_core_text_matcher_textmatcher_match_segments", "callee": "get", "is_member_call": true, "source_file": "D:\\QuranCaption\\src-tauri\\python\\segment_core\\text_matcher.py", "source_location": "L497"}, {"caller_nid": "segment_core_text_matcher_textmatcher_match_segments", "callee": "match_special_segment", "is_member_call": false, "source_file": "D:\\QuranCaption\\src-tauri\\python\\segment_core\\text_matcher.py", "source_location": "L501"}, {"caller_nid": "segment_core_text_matcher_textmatcher_match_segments", "callee": "match_special_segment", "is_member_call": false, "source_file": "D:\\QuranCaption\\src-tauri\\python\\segment_core\\text_matcher.py", "source_location": "L503"}, {"caller_nid": "segment_core_text_matcher_textmatcher_match_segments", "callee": "_add_special_result", "is_member_call": false, "source_file": "D:\\QuranCaption\\src-tauri\\python\\segment_core\\text_matcher.py", "source_location": "L506"}, {"caller_nid": "segment_core_text_matcher_textmatcher_match_segments", "callee": "strip", "is_member_call": true, "source_file": "D:\\QuranCaption\\src-tauri\\python\\segment_core\\text_matcher.py", "source_location": "L508"}, {"caller_nid": "segment_core_text_matcher_textmatcher_match_segments", "callee": "match_special_segment", "is_member_call": false, "source_file": "D:\\QuranCaption\\src-tauri\\python\\segment_core\\text_matcher.py", "source_location": "L509"}, {"caller_nid": "segment_core_text_matcher_textmatcher_match_segments", "callee": "_add_special_result", "is_member_call": false, "source_file": "D:\\QuranCaption\\src-tauri\\python\\segment_core\\text_matcher.py", "source_location": "L511"}, {"caller_nid": "segment_core_text_matcher_textmatcher_match_segments", "callee": "enumerate", "is_member_call": false, "source_file": "D:\\QuranCaption\\src-tauri\\python\\segment_core\\text_matcher.py", "source_location": "L515"}, {"caller_nid": "segment_core_text_matcher_textmatcher_match_segments", "callee": "strip", "is_member_call": true, "source_file": "D:\\QuranCaption\\src-tauri\\python\\segment_core\\text_matcher.py", "source_location": "L516"}, {"caller_nid": "segment_core_text_matcher_textmatcher_match_segments", "callee": "append", "is_member_call": true, "source_file": "D:\\QuranCaption\\src-tauri\\python\\segment_core\\text_matcher.py", "source_location": "L517"}, {"caller_nid": "segment_core_text_matcher_textmatcher_match_segments", "callee": "time", "is_member_call": true, "source_file": "D:\\QuranCaption\\src-tauri\\python\\segment_core\\text_matcher.py", "source_location": "L519"}, {"caller_nid": "segment_core_text_matcher_textmatcher_match_segments", "callee": "time", "is_member_call": true, "source_file": "D:\\QuranCaption\\src-tauri\\python\\segment_core\\text_matcher.py", "source_location": "L522"}, {"caller_nid": "segment_core_text_matcher_textmatcher_match_segments", "callee": "time", "is_member_call": true, "source_file": "D:\\QuranCaption\\src-tauri\\python\\segment_core\\text_matcher.py", "source_location": "L525"}, {"caller_nid": "segment_core_text_matcher_textmatcher_match_segments", "callee": "enumerate", "is_member_call": false, "source_file": "D:\\QuranCaption\\src-tauri\\python\\segment_core\\text_matcher.py", "source_location": "L527"}, {"caller_nid": "segment_core_text_matcher_textmatcher_match_segments", "callee": "strip", "is_member_call": true, "source_file": "D:\\QuranCaption\\src-tauri\\python\\segment_core\\text_matcher.py", "source_location": "L531"}, {"caller_nid": "segment_core_text_matcher_textmatcher_match_segments", "callee": "startswith", "is_member_call": true, "source_file": "D:\\QuranCaption\\src-tauri\\python\\segment_core\\text_matcher.py", "source_location": "L542"}, {"caller_nid": "segment_core_text_matcher_textmatcher_match_segments", "callee": "get", "is_member_call": true, "source_file": "D:\\QuranCaption\\src-tauri\\python\\segment_core\\text_matcher.py", "source_location": "L547"}, {"caller_nid": "segment_core_text_matcher_textmatcher_match_segments", "callee": "print", "is_member_call": false, "source_file": "D:\\QuranCaption\\src-tauri\\python\\segment_core\\text_matcher.py", "source_location": "L556"}, {"caller_nid": "segment_core_text_matcher_textmatcher_match_segments", "callee": "strip", "is_member_call": true, "source_file": "D:\\QuranCaption\\src-tauri\\python\\segment_core\\text_matcher.py", "source_location": "L557"}, {"caller_nid": "segment_core_text_matcher_textmatcher_match_segments", "callee": "time", "is_member_call": true, "source_file": "D:\\QuranCaption\\src-tauri\\python\\segment_core\\text_matcher.py", "source_location": "L570"}, {"caller_nid": "segment_core_text_matcher_textmatcher_match_segments", "callee": "time", "is_member_call": true, "source_file": "D:\\QuranCaption\\src-tauri\\python\\segment_core\\text_matcher.py", "source_location": "L571"}]}