{"nodes": [{"id": "d_qurancaption_src_routes_layout_ts", "label": "+layout.ts", "file_type": "code", "source_file": "D:\\QuranCaption\\src\\routes\\+layout.ts", "source_location": "L1"}, {"id": "routes_layout_load", "label": "load()", "file_type": "code", "source_file": "D:\\QuranCaption\\src\\routes\\+layout.ts", "source_location": "L15"}, {"id": "routes_layout_showerrordialog", "label": "showErrorDialog()", "file_type": "code", "source_file": "D:\\QuranCaption\\src\\routes\\+layout.ts", "source_location": "L49"}], "edges": [{"source": "d_qurancaption_src_routes_layout_ts", "target": "classes", "relation": "imports_from", "confidence": "EXTRACTED", "source_file": "D:\\QuranCaption\\src\\routes\\+layout.ts", "source_location": "L1", "weight": 1.0}, {"source": "d_qurancaption_src_routes_layout_ts", "target": "quran", "relation": "imports_from", "confidence": "EXTRACTED", "source_file": "D:\\QuranCaption\\src\\routes\\+layout.ts", "source_location": "L2", "weight": 1.0}, {"source": "d_qurancaption_src_routes_layout_ts", "target": "reciter", "relation": "imports_from", "confidence": "EXTRACTED", "source_file": "D:\\QuranCaption\\src\\routes\\+layout.ts", "source_location": "L3", "weight": 1.0}, {"source": "d_qurancaption_src_routes_layout_ts", "target": "settings_svelte", "relation": "imports_from", "confidence": "EXTRACTED", "source_file": "D:\\QuranCaption\\src\\routes\\+layout.ts", "source_location": "L4", "weight": 1.0}, {"source": "d_qurancaption_src_routes_layout_ts", "target": "modalmanager", "relation": "imports_from", "confidence": "EXTRACTED", "source_file": "D:\\QuranCaption\\src\\routes\\+layout.ts", "source_location": "L5", "weight": 1.0}, {"source": "d_qurancaption_src_routes_layout_ts", "target": "exportservice", "relation": "imports_from", "confidence": "EXTRACTED", "source_file": "D:\\QuranCaption\\src\\routes\\+layout.ts", "source_location": "L6", "weight": 1.0}, {"source": "d_qurancaption_src_routes_layout_ts", "target": "fontprovider", "relation": "imports_from", "confidence": "EXTRACTED", "source_file": "D:\\QuranCaption\\src\\routes\\+layout.ts", "source_location": "L7", "weight": 1.0}, {"source": "d_qurancaption_src_routes_layout_ts", "target": "analyticsservice", "relation": "imports_from", "confidence": "EXTRACTED", "source_file": "D:\\QuranCaption\\src\\routes\\+layout.ts", "source_location": "L9", "weight": 1.0}, {"source": "d_qurancaption_src_routes_layout_ts", "target": "routes_layout_load", "relation": "contains", "confidence": "EXTRACTED", "source_file": "D:\\QuranCaption\\src\\routes\\+layout.ts", "source_location": "L15", "weight": 1.0}, {"source": "d_qurancaption_src_routes_layout_ts", "target": "routes_layout_showerrordialog", "relation": "contains", "confidence": "EXTRACTED", "source_file": "D:\\QuranCaption\\src\\routes\\+layout.ts", "source_location": "L49", "weight": 1.0}], "raw_calls": [{"caller_nid": "routes_layout_load", "callee": "init", "is_member_call": true, "source_file": "D:\\QuranCaption\\src\\routes\\+layout.ts", "source_location": "L16"}, {"caller_nid": "routes_layout_showerrordialog", "callee": "error", "is_member_call": true, "source_file": "D:\\QuranCaption\\src\\routes\\+layout.ts", "source_location": "L50"}, {"caller_nid": "routes_layout_showerrordialog", "callee": "errorModal", "is_member_call": true, "source_file": "D:\\QuranCaption\\src\\routes\\+layout.ts", "source_location": "L52"}, {"caller_nid": "routes_layout_showerrordialog", "callee": "stringify", "is_member_call": true, "source_file": "D:\\QuranCaption\\src\\routes\\+layout.ts", "source_location": "L55"}, {"caller_nid": "routes_layout_showerrordialog", "callee": "getOwnPropertyNames", "is_member_call": true, "source_file": "D:\\QuranCaption\\src\\routes\\+layout.ts", "source_location": "L55"}, {"caller_nid": "routes_layout_showerrordialog", "callee": "trackError", "is_member_call": true, "source_file": "D:\\QuranCaption\\src\\routes\\+layout.ts", "source_location": "L59"}]}