{"1":{"w":[{"b":"0.09","h":"0.35","c":"حمٓ","d":"ha-meem","e":"Ha Meem","i":"حٰمٓ ​ ۛ​ۚ"}],"a":{"g":"Ha, Meem."}},"2":{"w":[{"b":"0.03","h":"1","c":"وَٱلۡكِتَٰبِ","d":"wal-kitābi","e":"By the Book","i":"وَالۡكِتٰبِ"},{"b":"1.2","h":"3.24","c":"ٱلۡمُبِينِ","d":"l-mubīni","e":"the clear","i":"الۡمُبِيۡنِ ​ ۛ​ۙ"}],"a":{"g":"By the clear Book,"}},"3":{"w":[{"b":"0.05","h":"0.6","c":"إِنَّآ","d":"innā","e":"Indeed We","i":"اِنَّاۤ"},{"b":"2.8","h":"1.94","c":"أَنزَلۡنَٰهُ","d":"anzalnāhu","e":"revealed it","i":"اَنۡزَلۡنٰهُ"},{"b":"5.3","h":"6.87","c":"فِي","d":"fī","e":"in","i":"فِىۡ"},{"b":"5.8","h":"7.66","c":"لَيۡلَةٖ","d":"laylatin","e":"a Night","i":"لَيۡلَةٍ"},{"b":"7.9","h":"9.91","c":"مُّبَٰرَكَةٍۚ","d":"mubārakatin","e":"Blessed","i":"مُّبٰـرَكَةٍ​"},{"b":"9.5","h":"13.9","c":"إِنَّا","d":"innā","e":"Indeed We","i":"اِنَّا"},{"b":"11.1","h":"15.66","c":"كُنَّا","d":"kunnā","e":"[We] are","i":"كُنَّا"},{"b":"13.0","h":"17.86","c":"مُنذِرِينَ","d":"mundhirīna","e":"(ever) warning","i":"مُنۡذِرِيۡنَ"}],"a":{"g":"Indeed, We sent it down during a blessed night. Indeed, We were to warn [mankind]."}},"4":{"w":[{"b":"0.03","h":"0","c":"فِيهَا","d":"fīhā","e":"Therein","i":"فِيۡهَا"},{"b":"0.91","h":"1.89","c":"يُفۡرَقُ","d":"yuf'raqu","e":"is made distinct","i":"يُفۡرَقُ"},{"b":"1.7","h":"3.36","c":"كُلُّ","d":"kullu","e":"every","i":"كُلُّ"},{"b":"2.4","h":"4.42","c":"أَمۡرٍ","d":"amrin","e":"affair","i":"اَمۡرٍ"},{"b":"3.1","h":"5.7","c":"حَكِيمٍ","d":"ḥakīmin","e":"wise","i":"حَكِيۡمٍۙ"}],"a":{"g":"On that night is made distinct every precise matter -"}},"5":{"w":[{"b":"0.05","h":"0.2","c":"أَمۡرٗا","d":"amran","e":"A command","i":"اَمۡرًا"},{"b":"0.64","h":"1.14","c":"مِّنۡ","d":"min","e":"from","i":"مِّنۡ"},{"b":"1.8","h":"2.44","c":"عِندِنَآۚ","d":"ʿindinā","e":"Us","i":"عِنۡدِنَا​ؕ"},{"b":"5.3","h":"6.54","c":"إِنَّا","d":"innā","e":"Indeed We","i":"اِنَّا"},{"b":"5.6","h":"8.27","c":"كُنَّا","d":"kunnā","e":"[We] are","i":"كُنَّا"},{"b":"7.3","h":"10.22","c":"مُرۡسِلِينَ","d":"mur'silīna","e":"(ever) sending","i":"مُرۡسِلِيۡنَ​ۚ"}],"a":{"g":"[Every] matter [proceeding] from Us. Indeed, We were to send [a messenger]"}},"6":{"w":[{"b":"0.05","h":"0.45","c":"رَحۡمَةٗ","d":"raḥmatan","e":"As Mercy","i":"رَحۡمَةً"},{"b":"1.9","h":"2.64","c":"مِّن","d":"min","e":"from","i":"مِّنۡ"},{"b":"1.9","h":"2.78","c":"رَّبِّكَۚ","d":"rabbika","e":"your Lord","i":"رَّبِّكَ​ؕ"},{"b":"3.5","h":"6","c":"إِنَّهُۥ","d":"innahu","e":"Indeed He","i":"اِنَّهٗ"},{"b":"5.1","h":"8.04","c":"هُوَ","d":"huwa","e":"[He]","i":"هُوَ"},{"b":"5.5","h":"8.75","c":"ٱلسَّمِيعُ","d":"l-samīʿu","e":"(is) the All-Hearer","i":"السَّمِيۡعُ"},{"b":"6.6","h":"10.76","c":"ٱلۡعَلِيمُ","d":"l-ʿalīmu","e":"the All-Knower","i":"الۡعَلِيۡمُۙ"}],"a":{"g":"As mercy from your Lord. Indeed, He is the Hearing, the Knowing."}},"7":{"w":[{"b":"0.03","h":"0.45","c":"رَبِّ","d":"rabbi","e":"Lord","i":"رَبِّ"},{"b":"0.55","h":"1.3","c":"ٱلسَّمَٰوَٰتِ","d":"l-samāwāti","e":"(of) the heavens","i":"السَّمٰوٰتِ"},{"b":"2.1","h":"3.67","c":"وَٱلۡأَرۡضِ","d":"wal-arḍi","e":"and the earth","i":"وَالۡاَرۡضِ"},{"b":"3.1","h":"5.38","c":"وَمَا","d":"wamā","e":"and whatever","i":"وَمَا"},{"b":"3.7","h":"6.49","c":"بَيۡنَهُمَآۖ","d":"baynahumā","e":"(is) between both of them","i":"بَيۡنَهُمَا​ۘ"},{"b":"5.6","h":"10.79","c":"إِن","d":"in","e":"if","i":"اِنۡ"},{"b":"7.2","h":"11.81","c":"كُنتُم","d":"kuntum","e":"you","i":"كُنۡتُمۡ"},{"b":"10.1","h":"14.72","c":"مُّوقِنِينَ","d":"mūqinīna","e":"would be certain","i":"مُّوۡقِنِيۡنَ"}],"a":{"g":"Lord of the heavens and the earth and that between them, if you would be certain."}},"8":{"w":[{"b":"0.03","h":"0.9","c":"لَآ","d":"lā","e":"(There is) no","i":"لَاۤ"},{"b":"2.2","h":"2.89","c":"إِلَٰهَ","d":"ilāha","e":"god","i":"اِلٰهَ"},{"b":"3.0","h":"4.26","c":"إِلَّا","d":"illā","e":"except","i":"اِلَّا"},{"b":"3.9","h":"5.78","c":"هُوَ","d":"huwa","e":"Him","i":"هُوَ"},{"b":"4.3","h":"6.61","c":"يُحۡيِۦ","d":"yuḥ'yī","e":"He gives life","i":"يُحۡىٖ"},{"b":"5.2","h":"8.16","c":"وَيُمِيتُۖ","d":"wayumītu","e":"and causes death","i":"وَيُمِيۡتُ​ؕ"},{"b":"8.0","h":"12.85","c":"رَبُّكُمۡ","d":"rabbukum","e":"your Lord","i":"رَبُّكُمۡ"},{"b":"9.1","h":"14.66","c":"وَرَبُّ","d":"warabbu","e":"and (the) Lord","i":"وَرَبُّ"},{"b":"9.9","h":"16.15","c":"ءَابَآئِكُمُ","d":"ābāikumu","e":"(of) your fathers","i":"اٰبَآٮِٕكُمُ"},{"b":"13.1","h":"19.83","c":"ٱلۡأَوَّلِينَ","d":"l-awalīna","e":"the former","i":"الۡاَوَّلِيۡنَ"}],"a":{"g":"There is no deity except Him; He gives life and causes death. [He is] your Lord and the Lord of your first forefathers."}},"9":{"w":[{"b":"0.1","h":"1.15","c":"بَلۡ","d":"bal","e":"Nay","i":"بَلۡ"},{"b":"0.48","h":"1.71","c":"هُمۡ","d":"hum","e":"they","i":"هُمۡ"},{"b":"0.87","h":"2.45","c":"فِي","d":"fī","e":"(are) in","i":"فِىۡ"},{"b":"1.3","h":"3.24","c":"شَكّٖ","d":"shakkin","e":"doubt","i":"شَكٍّ"},{"b":"2.8","h":"5.31","c":"يَلۡعَبُونَ","d":"yalʿabūna","e":"playing","i":"يَّلۡعَبُوۡنَ"}],"a":{"g":"But they are in doubt, amusing themselves."}},"10":{"w":[{"b":"0.03","h":"0.6","c":"فَٱرۡتَقِبۡ","d":"fa-ir'taqib","e":"Then watch","i":"فَارۡتَقِبۡ"},{"b":"1","h":"2.2","c":"يَوۡمَ","d":"yawma","e":"(for the) Day","i":"يَوۡمَ"},{"b":"1.5","h":"3.31","c":"تَأۡتِي","d":"tatī","e":"(when) will bring","i":"تَاۡتِى"},{"b":"2.2","h":"4.48","c":"ٱلسَّمَآءُ","d":"l-samāu","e":"the sky","i":"السَّمَآءُ"},{"b":"4.9","h":"7.15","c":"بِدُخَانٖ","d":"bidukhānin","e":"smoke","i":"بِدُخَانٍ"},{"b":"5.9","h":"10.01","c":"مُّبِينٖ","d":"mubīnin","e":"visible","i":"مُّبِيۡنٍۙ"}],"a":{"g":"Then watch for the Day when the sky will bring a visible smoke."}},"11":{"w":[{"b":"0.08","h":"0.35","c":"يَغۡشَى","d":"yaghshā","e":"Enveloping","i":"يَغۡشَى"},{"b":"0.75","h":"1.43","c":"ٱلنَّاسَۖ","d":"l-nāsa","e":"the people","i":"النَّاسَ​ؕ"},{"b":"4.8","h":"5.8","c":"هَٰذَا","d":"hādhā","e":"This","i":"هٰذَا"},{"b":"5.6","h":"7.23","c":"عَذَابٌ","d":"ʿadhābun","e":"(will be) a punishment","i":"عَذَابٌ"},{"b":"6.7","h":"9.38","c":"أَلِيمٞ","d":"alīmun","e":"painful","i":"اَلِيۡمٌ"}],"a":{"g":"Covering the people; this is a painful torment."}},"12":{"w":[{"b":"0.04","h":"0.45","c":"رَّبَّنَا","d":"rabbanā","e":"Our Lord!","i":"رَبَّنَا"},{"b":"0.79","h":"1.59","c":"ٱكۡشِفۡ","d":"ik'shif","e":"Remove","i":"اكۡشِفۡ"},{"b":"1.4","h":"2.65","c":"عَنَّا","d":"ʿannā","e":"from us","i":"عَنَّا"},{"b":"2.7","h":"4.1","c":"ٱلۡعَذَابَ","d":"l-ʿadhāba","e":"the punishment","i":"الۡعَذَابَ"},{"b":"3.8","h":"5.87","c":"إِنَّا","d":"innā","e":"indeed we","i":"اِنَّا"},{"b":"5.5","h":"7.7","c":"مُؤۡمِنُونَ","d":"mu'minūna","e":"(are) believers","i":"مُؤۡمِنُوۡنَ"}],"a":{"g":"[They will say], \"Our Lord, remove from us the torment; indeed, we are believers.\""}},"13":{"w":[{"b":"0.08","h":"0.5","c":"أَنَّىٰ","d":"annā","e":"How can","i":"اَنّٰى"},{"b":"1.4","h":"2.26","c":"لَهُمُ","d":"lahumu","e":"(there be) for them","i":"لَهُمُ"},{"b":"2.1","h":"3.31","c":"ٱلذِّكۡرَىٰ","d":"l-dhik'rā","e":"the reminder","i":"الذِّكۡرٰى"},{"b":"3.2","h":"5.23","c":"وَقَدۡ","d":"waqad","e":"when verily","i":"وَقَدۡ"},{"b":"3.8","h":"6.32","c":"جَآءَهُمۡ","d":"jāahum","e":"had come to them","i":"جَآءَهُمۡ"},{"b":"6.4","h":"8.87","c":"رَسُولٞ","d":"rasūlun","e":"a Messenger","i":"رَسُوۡلٌ"},{"b":"8.2","h":"11.64","c":"مُّبِينٞ","d":"mubīnun","e":"clear","i":"مُّبِيۡنٌۙ"}],"a":{"g":"How will there be for them a reminder [at that time]? And there had come to them a clear Messenger."}},"14":{"w":[{"b":"0.03","h":"0.65","c":"ثُمَّ","d":"thumma","e":"Then","i":"ثُمَّ"},{"b":"1.2","h":"1.98","c":"تَوَلَّوۡاْ","d":"tawallaw","e":"they turned away","i":"تَوَلَّوۡا"},{"b":"2.2","h":"3.62","c":"عَنۡهُ","d":"ʿanhu","e":"from him","i":"عَنۡهُ"},{"b":"3.0","h":"4.9","c":"وَقَالُواْ","d":"waqālū","e":"and said","i":"وَقَالُوۡا"},{"b":"4.1","h":"6.78","c":"مُعَلَّمٞ","d":"muʿallamun","e":"One taught","i":"مُعَلَّمٌ"},{"b":"5.8","h":"9.3","c":"مَّجۡنُونٌ","d":"majnūnun","e":"a mad man","i":"مَّجۡنُوۡنٌ​ۘ"}],"a":{"g":"Then they turned away from him and said, \"[He was] taught [and is] a madman.\""}},"15":{"w":[{"b":"0.03","h":"0.8","c":"إِنَّا","d":"innā","e":"Indeed We","i":"اِنَّا"},{"b":"1.2","h":"2.77","c":"كَاشِفُواْ","d":"kāshifū","e":"(will) remove","i":"كَاشِفُوا"},{"b":"2.2","h":"4.35","c":"ٱلۡعَذَابِ","d":"l-ʿadhābi","e":"the punishment","i":"الۡعَذَابِ"},{"b":"3.3","h":"6.11","c":"قَلِيلًاۚ","d":"qalīlan","e":"a little","i":"قَلِيۡلًا"},{"b":"5.0","h":"9.35","c":"إِنَّكُمۡ","d":"innakum","e":"indeed you","i":"اِنَّكُمۡ"},{"b":"6.7","h":"11.37","c":"عَآئِدُونَ","d":"ʿāidūna","e":"(will) return","i":"عَآٮِٕدُوۡنَ​ۘ"}],"a":{"g":"Indeed, We will remove the torment for a little. Indeed, you [disbelievers] will return [to disbelief]."}},"16":{"w":[{"b":"0.05","h":"0.85","c":"يَوۡمَ","d":"yawma","e":"(The) Day","i":"يَوۡمَ"},{"b":"0.67","h":"1.79","c":"نَبۡطِشُ","d":"nabṭishu","e":"We will seize","i":"نَبۡطِشُ"},{"b":"1.5","h":"3.11","c":"ٱلۡبَطۡشَةَ","d":"l-baṭshata","e":"(with) the seizure","i":"الۡبَطۡشَةَ"},{"b":"2.5","h":"4.83","c":"ٱلۡكُبۡرَىٰٓ","d":"l-kub'rā","e":"the greatest","i":"الۡكُبۡـرٰى​ۚ"},{"b":"5.0","h":"7.75","c":"إِنَّا","d":"innā","e":"indeed We","i":"اِنَّا"},{"b":"6.5","h":"9.7","c":"مُنتَقِمُونَ","d":"muntaqimūna","e":"(will) take retribution","i":"مُنۡتَقِمُوۡنَ"}],"a":{"g":"The Day We will strike with the greatest assault, indeed, We will take retribution."}},"17":{"w":[{"b":"0.08","h":"0.95","c":"وَلَقَدۡ","d":"walaqad","e":"And certainly","i":"۞ وَلَقَدۡ"},{"b":"0.88","h":"2.08","c":"فَتَنَّا","d":"fatannā","e":"We tried","i":"فَتَنَّا"},{"b":"2.6","h":"4.45","c":"قَبۡلَهُمۡ","d":"qablahum","e":"before them","i":"قَبۡلَهُمۡ"},{"b":"3.7","h":"6.21","c":"قَوۡمَ","d":"qawma","e":"(the) people","i":"قَوۡمَ"},{"b":"4.4","h":"7.32","c":"فِرۡعَوۡنَ","d":"fir'ʿawna","e":"(of) Firaun","i":"فِرۡعَوۡنَ"},{"b":"5.5","h":"9.19","c":"وَجَآءَهُمۡ","d":"wajāahum","e":"and came to them","i":"وَ جَآءَهُمۡ"},{"b":"8.5","h":"12.32","c":"رَسُولٞ","d":"rasūlun","e":"a Messenger","i":"رَسُوۡلٌ"},{"b":"10.5","h":"14.64","c":"كَرِيمٌ","d":"karīmun","e":"noble","i":"كَرِيۡمٌۙ"}],"a":{"g":"And We had already tried before them the people of Pharaoh, and there came to them a noble messenger,"}},"18":{"w":[{"b":"0.06","h":"0.8","c":"أَنۡ","d":"an","e":"That","i":"اَنۡ"},{"b":"0.42","h":"1.47","c":"أَدُّوٓاْ","d":"addū","e":"Deliver","i":"اَدُّوۡۤا"},{"b":"3.0","h":"4.04","c":"إِلَيَّ","d":"ilayya","e":"to me","i":"اِلَىَّ"},{"b":"3.8","h":"5.45","c":"عِبَادَ","d":"ʿibāda","e":"(the) servants","i":"عِبَادَ"},{"b":"4.8","h":"6.99","c":"ٱللَّهِۖ","d":"l-lahi","e":"(of) Allah","i":"اللّٰهِ​ؕ"},{"b":"8.0","h":"10.95","c":"إِنِّي","d":"innī","e":"Indeed I am","i":"اِنِّىۡ"},{"b":"9.7","h":"12.85","c":"لَكُمۡ","d":"lakum","e":"to you","i":"لَـكُمۡ"},{"b":"10.3","h":"13.88","c":"رَسُولٌ","d":"rasūlun","e":"a Messenger","i":"رَسُوۡلٌ"},{"b":"11.4","h":"15.9","c":"أَمِينٞ","d":"amīnun","e":"trustworthy","i":"اَمِيۡنٌۙ"}],"a":{"g":"[Saying], \"Render to me the servants of Allah. Indeed, I am to you a trustworthy messenger,\""}},"19":{"w":[{"b":"0.03","h":"0.55","c":"وَأَن","d":"wa-an","e":"And that","i":"وَّاَنۡ"},{"b":"0.36","h":"1.04","c":"لَّا","d":"lā","e":"(do) not","i":"لَّا"},{"b":"1.0","h":"2.1","c":"تَعۡلُواْ","d":"taʿlū","e":"exalt yourselves","i":"تَعۡلُوۡا"},{"b":"1.9","h":"3.67","c":"عَلَى","d":"ʿalā","e":"against","i":"عَلَى"},{"b":"2.4","h":"4.45","c":"ٱللَّهِۖ","d":"l-lahi","e":"Allah","i":"اللّٰهِ​ۚ"},{"b":"4.8","h":"8.35","c":"إِنِّيٓ","d":"innī","e":"Indeed I","i":"اِنِّىۡۤ"},{"b":"8.0","h":"11.23","c":"ءَاتِيكُم","d":"ātīkum","e":"[I] have come to you","i":"اٰتِيۡكُمۡ"},{"b":"10.1","h":"13.92","c":"بِسُلۡطَٰنٖ","d":"bisul'ṭānin","e":"with an authority","i":"بِسُلۡطٰنٍ"},{"b":"12.2","h":"17.49","c":"مُّبِينٖ","d":"mubīnin","e":"clear","i":"مُّبِيۡنٍ​ۚ"}],"a":{"g":"And [saying], \"Be not haughty with Allah. Indeed, I have come to you with clear authority."}},"20":{"w":[{"b":"0.04","h":"0.3","c":"وَإِنِّي","d":"wa-innī","e":"And indeed I","i":"وَاِنِّىۡ"},{"b":"1.6","h":"2.24","c":"عُذۡتُ","d":"ʿudh'tu","e":"[I] seek refuge","i":"عُذۡتُ"},{"b":"2.4","h":"3.61","c":"بِرَبِّي","d":"birabbī","e":"with my Lord","i":"بِرَبِّىۡ"},{"b":"3.5","h":"5.6","c":"وَرَبِّكُمۡ","d":"warabbikum","e":"and your Lord","i":"وَرَبِّكُمۡ"},{"b":"4.9","h":"7.85","c":"أَن","d":"an","e":"lest","i":"اَنۡ"},{"b":"6.0","h":"9.14","c":"تَرۡجُمُونِ","d":"tarjumūni","e":"you stone me","i":"تَرۡجُمُوۡنِ ۚ"}],"a":{"g":"And indeed, I have sought refuge in my Lord and your Lord, lest you stone me."}},"21":{"w":[{"b":"0.05","h":"0.7","c":"وَإِن","d":"wa-in","e":"And if","i":"وَاِنۡ"},{"b":"0.5","h":"1.6","c":"لَّمۡ","d":"lam","e":"not","i":"لَّمۡ"},{"b":"1.0","h":"2.3","c":"تُؤۡمِنُواْ","d":"tu'minū","e":"you believe","i":"تُؤۡمِنُوۡا"},{"b":"2.2","h":"4.35","c":"لِي","d":"lī","e":"me","i":"لِىۡ"},{"b":"2.6","h":"4.98","c":"فَٱعۡتَزِلُونِ","d":"fa-iʿ'tazilūni","e":"then leave me alone","i":"فَاعۡتَزِلُوۡنِ"}],"a":{"g":"But if you do not believe me, then leave me alone.\""}},"22":{"w":[{"b":"0.03","h":"0.9","c":"فَدَعَا","d":"fadaʿā","e":"So he called","i":"فَدَعَا"},{"b":"0.89","h":"2.23","c":"رَبَّهُۥٓ","d":"rabbahu","e":"his Lord","i":"رَبَّهٗۤ"},{"b":"3.6","h":"5.08","c":"أَنَّ","d":"anna","e":"That","i":"اَنَّ"},{"b":"5.0","h":"6.65","c":"هَـٰٓؤُلَآءِ","d":"hāulāi","e":"these","i":"هٰٓؤُلَاۤءِ"},{"b":"10.3","h":"10.54","c":"قَوۡمٞ","d":"qawmun","e":"(are) a people","i":"قَوۡمٌ"},{"b":"11.6","h":"12.7","c":"مُّجۡرِمُونَ","d":"muj'rimūna","e":"criminals","i":"مُّجۡرِمُوۡنَ"}],"a":{"g":"And [finally] he called to his Lord that these were a criminal people."}},"23":{"w":[{"b":"0.03","h":"0.35","c":"فَأَسۡرِ","d":"fa-asri","e":"Then Set out","i":"فَاَسۡرِ"},{"b":"0.89","h":"1.53","c":"بِعِبَادِي","d":"biʿibādī","e":"with My slaves","i":"بِعِبَادِىۡ"},{"b":"2.2","h":"3.71","c":"لَيۡلًا","d":"laylan","e":"(by) night","i":"لَيۡلًا"},{"b":"3.0","h":"5.09","c":"إِنَّكُم","d":"innakum","e":"Indeed you","i":"اِنَّكُمۡ"},{"b":"5.4","h":"7.97","c":"مُّتَّبَعُونَ","d":"muttabaʿūna","e":"(will be) followed","i":"مُّتَّبَعُوۡنَۙ"}],"a":{"g":"[Allah said], \"Then set out with My servants by night. Indeed, you are to be pursued."}},"24":{"w":[{"b":"0.07","h":"0.45","c":"وَٱتۡرُكِ","d":"wa-ut'ruki","e":"And leave","i":"وَاتۡرُكِ"},{"b":"0.98","h":"1.72","c":"ٱلۡبَحۡرَ","d":"l-baḥra","e":"the sea","i":"الۡبَحۡرَ"},{"b":"1.8","h":"3.24","c":"رَهۡوًاۖ","d":"rahwan","e":"at rest","i":"رَهۡوًا​ؕ"},{"b":"2.6","h":"6.05","c":"إِنَّهُمۡ","d":"innahum","e":"Indeed they","i":"اِنَّهُمۡ"},{"b":"4.5","h":"8.2","c":"جُندٞ","d":"jundun","e":"(are) an army","i":"جُنۡدٌ"},{"b":"7.2","h":"11.09","c":"مُّغۡرَقُونَ","d":"mugh'raqūna","e":"(to be) drowned","i":"مُّغۡرَقُوۡنَ"}],"a":{"g":"And leave the sea in stillness. Indeed, they are an army to be drowned.\""}},"25":{"w":[{"b":"0.04","h":"0.3","c":"كَمۡ","d":"kam","e":"How many","i":"كَمۡ"},{"b":"0.43","h":"0.77","c":"تَرَكُواْ","d":"tarakū","e":"(did) they leave","i":"تَرَكُوۡا"},{"b":"1.3","h":"2.35","c":"مِن","d":"min","e":"of","i":"مِنۡ"},{"b":"2.4","h":"3.46","c":"جَنَّـٰتٖ","d":"jannātin","e":"gardens","i":"جَنّٰتٍ"},{"b":"4.4","h":"6.71","c":"وَعُيُونٖ","d":"waʿuyūnin","e":"and springs","i":"وَّعُيُوۡنٍۙ"}],"a":{"g":"How much they left behind of gardens and springs"}},"26":{"w":[{"b":"0.03","h":"0.55","c":"وَزُرُوعٖ","d":"wazurūʿin","e":"And cornfields","i":"وَّزُرُوۡعٍ"},{"b":"1.2","h":"2.96","c":"وَمَقَامٖ","d":"wamaqāmin","e":"and places","i":"وَّمَقَامٍ"},{"b":"4.2","h":"5.78","c":"كَرِيمٖ","d":"karīmin","e":"noble","i":"كَرِيۡمٍۙ"}],"a":{"g":"And crops and noble sites"}},"27":{"w":[{"b":"0.06","h":"0.35","c":"وَنَعۡمَةٖ","d":"wanaʿmatin","e":"And pleasant things","i":"وَّنَعۡمَةٍ"},{"b":"2","h":"2.81","c":"كَانُواْ","d":"kānū","e":"they used (to)","i":"كَانُوۡا"},{"b":"2.9","h":"4.4","c":"فِيهَا","d":"fīhā","e":"therein","i":"فِيۡهَا"},{"b":"3.8","h":"6.05","c":"فَٰكِهِينَ","d":"fākihīna","e":"take delight!","i":"فٰكِهِيۡنَۙ"}],"a":{"g":"And comfort wherein they were amused."}},"28":{"w":[{"b":"0.05","h":"0.75","c":"كَذَٰلِكَۖ","d":"kadhālika","e":"Thus","i":"كَذٰلِكَ​"},{"b":"1.6","h":"2.43","c":"وَأَوۡرَثۡنَٰهَا","d":"wa-awrathnāhā","e":"And We made it (an) inherit(ance)","i":"وَاَوۡرَثۡنٰهَا"},{"b":"3.5","h":"5.79","c":"قَوۡمًا","d":"qawman","e":"(for) a people","i":"قَوۡمًا"},{"b":"4.4","h":"7.41","c":"ءَاخَرِينَ","d":"ākharīna","e":"another","i":"اٰخَرِيۡنَ"}],"a":{"g":"Thus. And We caused to inherit it another people."}},"29":{"w":[{"b":"0.03","h":"0.35","c":"فَمَا","d":"famā","e":"And not","i":"فَمَا"},{"b":"0.6","h":"1.31","c":"بَكَتۡ","d":"bakat","e":"wept","i":"بَكَتۡ"},{"b":"1.2","h":"2.32","c":"عَلَيۡهِمُ","d":"ʿalayhimu","e":"for them","i":"عَلَيۡهِمُ"},{"b":"2.3","h":"4.29","c":"ٱلسَّمَآءُ","d":"l-samāu","e":"the heaven","i":"السَّمَآءُ"},{"b":"4.9","h":"6.83","c":"وَٱلۡأَرۡضُ","d":"wal-arḍu","e":"and the earth","i":"وَالۡاَرۡضُ"},{"b":"5.9","h":"8.54","c":"وَمَا","d":"wamā","e":"and not","i":"وَمَا"},{"b":"6.6","h":"9.63","c":"كَانُواْ","d":"kānū","e":"they were","i":"كَانُوۡا"},{"b":"7.5","h":"11.21","c":"مُنظَرِينَ","d":"munẓarīna","e":"given respite","i":"مُنۡظَرِيۡنَ"}],"a":{"g":"And the heaven and earth wept not for them, nor were they reprieved."}},"30":{"w":[{"b":"0.07","h":"0.85","c":"وَلَقَدۡ","d":"walaqad","e":"And certainly","i":"وَلَقَدۡ"},{"b":"0.91","h":"2.08","c":"نَجَّيۡنَا","d":"najjaynā","e":"We saved","i":"نَجَّيۡنَا"},{"b":"2.0","h":"4.3","c":"بَنِيٓ","d":"banī","e":"(the) Children of Israel","i":"بَنِىۡۤ"},{"b":"4.2","h":"6.24","c":"إِسۡرَـٰٓءِيلَ","d":"is'rāīla","e":"(the) Children of Israel","i":"اِسۡرَآءِيۡلَ"},{"b":"7.4","h":"9.72","c":"مِنَ","d":"mina","e":"from","i":"مِنَ"},{"b":"7.8","h":"10.29","c":"ٱلۡعَذَابِ","d":"l-ʿadhābi","e":"the punishment","i":"الۡعَذَابِ"},{"b":"9","h":"12.39","c":"ٱلۡمُهِينِ","d":"l-muhīni","e":"the humiliating","i":"الۡمُهِيۡنِۙ"}],"a":{"g":"And We certainly saved the Children of Israel from the humiliating torment -"}},"31":{"w":[{"b":"0.04","h":"0.3","c":"مِن","d":"min","e":"From","i":"مِنۡ"},{"b":"1.2","h":"1.3","c":"فِرۡعَوۡنَۚ","d":"fir'ʿawna","e":"Firaun","i":"فِرۡعَوۡنَ​ؕ"},{"b":"5","h":"7.3","c":"إِنَّهُۥ","d":"innahu","e":"Indeed he","i":"اِنَّهٗ"},{"b":"6.3","h":"9.39","c":"كَانَ","d":"kāna","e":"was","i":"كَانَ"},{"b":"7.0","h":"10.41","c":"عَالِيٗا","d":"ʿāliyan","e":"arrogant","i":"عَالِيًا"},{"b":"8.8","h":"13.09","c":"مِّنَ","d":"mina","e":"among","i":"مِّنَ"},{"b":"9.1","h":"13.61","c":"ٱلۡمُسۡرِفِينَ","d":"l-mus'rifīna","e":"the transgressors","i":"الۡمُسۡرِفِيۡنَ"}],"a":{"g":"From Pharaoh. Indeed, he was a haughty one among the transgressors."}},"32":{"w":[{"b":"0.06","h":"0.95","c":"وَلَقَدِ","d":"walaqadi","e":"And certainly","i":"وَلَقَدِ"},{"b":"0.82","h":"2.08","c":"ٱخۡتَرۡنَٰهُمۡ","d":"ikh'tarnāhum","e":"We chose them","i":"اخۡتَرۡنٰهُمۡ"},{"b":"2.4","h":"4.63","c":"عَلَىٰ","d":"ʿalā","e":"by","i":"عَلٰى"},{"b":"3.0","h":"5.82","c":"عِلۡمٍ","d":"ʿil'min","e":"knowledge","i":"عِلۡمٍ"},{"b":"3.8","h":"7.24","c":"عَلَى","d":"ʿalā","e":"over","i":"عَلَى"},{"b":"4.3","h":"8.02","c":"ٱلۡعَٰلَمِينَ","d":"l-ʿālamīna","e":"the worlds","i":"الۡعٰلَمِيۡنَ​ۚ"}],"a":{"g":"And We certainly chose them by knowledge over [all] the worlds."}},"33":{"w":[{"b":"0.03","h":"0.7","c":"وَءَاتَيۡنَٰهُم","d":"waātaynāhum","e":"And We gave them","i":"وَاٰتَيۡنٰهُمۡ"},{"b":"2.4","h":"4.52","c":"مِّنَ","d":"mina","e":"of","i":"مِّنَ"},{"b":"2.7","h":"5.13","c":"ٱلۡأٓيَٰتِ","d":"l-āyāti","e":"the Signs","i":"الۡاٰيٰتِ"},{"b":"4.1","h":"7.62","c":"مَا","d":"mā","e":"that","i":"مَا"},{"b":"4.5","h":"8.41","c":"فِيهِ","d":"fīhi","e":"in it","i":"فِيۡهِ"},{"b":"5.2","h":"9.65","c":"بَلَـٰٓؤٞاْ","d":"balāon","e":"(was) a trial","i":"بَلٰٓؤٌا"},{"b":"7.7","h":"12.73","c":"مُّبِينٌ","d":"mubīnun","e":"clear","i":"مُّبِيۡنٌ"}],"a":{"g":"And We gave them of signs that in which there was a clear trial."}},"34":{"w":[{"b":"0.09","h":"0.8","c":"إِنَّ","d":"inna","e":"Indeed","i":"اِنَّ"},{"b":"1.4","h":"2.35","c":"هَـٰٓؤُلَآءِ","d":"hāulāi","e":"these","i":"هٰٓؤُلَاۤءِ"},{"b":"6.1","h":"6.35","c":"لَيَقُولُونَ","d":"layaqūlūna","e":"surely they say","i":"لَيَقُوۡلُوۡنَۙ"}],"a":{"g":"Indeed, these [disbelievers] are saying,"}},"35":{"w":[{"b":"0.03","h":"0.5","c":"إِنۡ","d":"in","e":"Not","i":"اِنۡ"},{"b":"0.38","h":"1.04","c":"هِيَ","d":"hiya","e":"it","i":"هِىَ"},{"b":"0.87","h":"1.8","c":"إِلَّا","d":"illā","e":"(is) but","i":"اِلَّا"},{"b":"1.7","h":"3.21","c":"مَوۡتَتُنَا","d":"mawtatunā","e":"our death","i":"مَوۡتَتُنَا"},{"b":"2.8","h":"4.95","c":"ٱلۡأُولَىٰ","d":"l-ūlā","e":"the first","i":"الۡاُوۡلٰى"},{"b":"3.8","h":"6.82","c":"وَمَا","d":"wamā","e":"and not","i":"وَمَا"},{"b":"4.5","h":"8.02","c":"نَحۡنُ","d":"naḥnu","e":"we","i":"نَحۡنُ"},{"b":"5.1","h":"9.07","c":"بِمُنشَرِينَ","d":"bimunsharīna","e":"(will be) raised again","i":"بِمُنۡشَرِيۡنَ"}],"a":{"g":"\"There is not but our first death, and we will not be resurrected."}},"36":{"w":[{"b":"0.03","h":"0.85","c":"فَأۡتُواْ","d":"fatū","e":"Then bring","i":"فَاۡتُوۡا"},{"b":"0.82","h":"2.2","c":"بِـَٔابَآئِنَآ","d":"biābāinā","e":"our forefathers","i":"بِاٰبَآٮِٕنَاۤ"},{"b":"5.0","h":"6.95","c":"إِن","d":"in","e":"if","i":"اِنۡ"},{"b":"6.7","h":"8.25","c":"كُنتُمۡ","d":"kuntum","e":"you are","i":"كُنۡتُمۡ"},{"b":"8.2","h":"10.25","c":"صَٰدِقِينَ","d":"ṣādiqīna","e":"truthful","i":"صٰدِقِيۡنَ"}],"a":{"g":"Then bring [back] our forefathers, if you should be truthful.\""}},"37":{"w":[{"b":"0.05","h":"0.75","c":"أَهُمۡ","d":"ahum","e":"Are they","i":"اَهُمۡ"},{"b":"0.61","h":"1.61","c":"خَيۡرٌ","d":"khayrun","e":"better","i":"خَيۡرٌ"},{"b":"1.4","h":"3.05","c":"أَمۡ","d":"am","e":"or","i":"اَمۡ"},{"b":"1.8","h":"3.82","c":"قَوۡمُ","d":"qawmu","e":"(the) people","i":"قَوۡمُ"},{"b":"2.5","h":"5.03","c":"تُبَّعٖ","d":"tubbaʿin","e":"(of) Tubba","i":"تُبَّعٍۙ"},{"b":"3.6","h":"7.29","c":"وَٱلَّذِينَ","d":"wa-alladhīna","e":"and those","i":"وَّ الَّذِيۡنَ"},{"b":"5.5","h":"9.46","c":"مِن","d":"min","e":"before them","i":"مِنۡ"},{"b":"6.6","h":"10.53","c":"قَبۡلِهِمۡ","d":"qablihim","e":"before them","i":"قَبۡلِهِمۡ​ؕ"},{"b":"8.2","h":"13.95","c":"أَهۡلَكۡنَٰهُمۡۚ","d":"ahlaknāhum","e":"We destroyed them","i":"اَهۡلَكۡنٰهُمۡ​"},{"b":"9.9","h":"16.94","c":"إِنَّهُمۡ","d":"innahum","e":"indeed, they","i":"اِنَّهُمۡ"},{"b":"11.5","h":"19.32","c":"كَانُواْ","d":"kānū","e":"were","i":"كَانُوۡا"},{"b":"12.3","h":"21.05","c":"مُجۡرِمِينَ","d":"muj'rimīna","e":"criminals","i":"مُجۡرِمِيۡنَ"}],"a":{"g":"Are they better or the people of Tubba' and those before them? We destroyed them, [for] indeed, they were criminals."}},"38":{"w":[{"b":"0.03","h":"0.75","c":"وَمَا","d":"wamā","e":"And not","i":"وَمَا"},{"b":"0.57","h":"1.67","c":"خَلَقۡنَا","d":"khalaqnā","e":"We created","i":"خَلَقۡنَا"},{"b":"1.4","h":"3.09","c":"ٱلسَّمَٰوَٰتِ","d":"l-samāwāti","e":"the heavens","i":"السَّمٰوٰتِ"},{"b":"3.0","h":"5.83","c":"وَٱلۡأَرۡضَ","d":"wal-arḍa","e":"and the earth","i":"وَالۡاَرۡضَ"},{"b":"4.0","h":"7.63","c":"وَمَا","d":"wamā","e":"and whatever","i":"وَمَا"},{"b":"4.6","h":"8.69","c":"بَيۡنَهُمَا","d":"baynahumā","e":"(is) between them","i":"بَيۡنَهُمَا"},{"b":"5.9","h":"11.16","c":"لَٰعِبِينَ","d":"lāʿibīna","e":"(in) play","i":"لٰعِبِيۡنَ"}],"a":{"g":"And We did not create the heavens and earth and that between them in play."}},"39":{"w":[{"b":"0.17","h":"0.9","c":"مَا","d":"mā","e":"Not","i":"مَا"},{"b":"0.45","h":"1.49","c":"خَلَقۡنَٰهُمَآ","d":"khalaqnāhumā","e":"We created both of them","i":"خَلَقۡنٰهُمَاۤ"},{"b":"3.5","h":"5.49","c":"إِلَّا","d":"illā","e":"but","i":"اِلَّا"},{"b":"4.3","h":"6.9","c":"بِٱلۡحَقِّ","d":"bil-ḥaqi","e":"in [the] truth","i":"بِالۡحَقِّ"},{"b":"5.3","h":"8.68","c":"وَلَٰكِنَّ","d":"walākinna","e":"but","i":"وَلٰكِنَّ"},{"b":"7.2","h":"11.5","c":"أَكۡثَرَهُمۡ","d":"aktharahum","e":"most of them","i":"اَكۡثَرَهُمۡ"},{"b":"8.5","h":"13.74","c":"لَا","d":"lā","e":"(do) not","i":"لَا"},{"b":"8.9","h":"14.65","c":"يَعۡلَمُونَ","d":"yaʿlamūna","e":"know","i":"يَعۡلَمُوۡنَ"}],"a":{"g":"We did not create them except in truth, but most of them do not know."}},"40":{"w":[{"b":"0.03","h":"0.55","c":"إِنَّ","d":"inna","e":"Indeed","i":"اِنَّ"},{"b":"1.3","h":"1.89","c":"يَوۡمَ","d":"yawma","e":"(the) Day of Judgment","i":"يَوۡمَ"},{"b":"2","h":"2.96","c":"ٱلۡفَصۡلِ","d":"l-faṣli","e":"(the) Day of Judgment","i":"الۡفَصۡلِ"},{"b":"2.8","h":"4.55","c":"مِيقَٰتُهُمۡ","d":"mīqātuhum","e":"(is) an appointed term for them","i":"مِيۡقَاتُهُمۡ"},{"b":"4.3","h":"7.44","c":"أَجۡمَعِينَ","d":"ajmaʿīna","e":"all","i":"اَجۡمَعِيۡنَۙ"}],"a":{"g":"Indeed, the Day of Judgement is the appointed time for them all -"}},"41":{"w":[{"b":"0.06","h":"0.55","c":"يَوۡمَ","d":"yawma","e":"(The) Day","i":"يَوۡمَ"},{"b":"0.66","h":"1.57","c":"لَا","d":"lā","e":"not","i":"لَا"},{"b":"1.0","h":"2.23","c":"يُغۡنِي","d":"yugh'nī","e":"will avail","i":"يُغۡنِىۡ"},{"b":"1.9","h":"3.7","c":"مَوۡلًى","d":"mawlan","e":"a relation","i":"مَوۡلًى"},{"b":"2.7","h":"5.17","c":"عَن","d":"ʿan","e":"for","i":"عَنۡ"},{"b":"3.9","h":"5.54","c":"مَّوۡلٗى","d":"mawlan","e":"a relation","i":"مَّوۡلًى"},{"b":"5.3","h":"7.59","c":"شَيۡـٔٗا","d":"shayan","e":"anything","i":"شَيۡــًٔا"},{"b":"6.0","h":"9.47","c":"وَلَا","d":"walā","e":"and not","i":"وَّلَا"},{"b":"7.5","h":"11.21","c":"هُمۡ","d":"hum","e":"they","i":"هُمۡ"},{"b":"8","h":"12.1","c":"يُنصَرُونَ","d":"yunṣarūna","e":"will be helped","i":"يُنۡصَرُوۡنَۙ"}],"a":{"g":"The Day when no relation will avail a relation at all, nor will they be helped -"}},"42":{"w":[{"b":"0.05","h":"0.85","c":"إِلَّا","d":"illā","e":"Except","i":"اِلَّا"},{"b":"0.89","h":"2.23","c":"مَن","d":"man","e":"(on) whom","i":"مَنۡ"},{"b":"1.0","h":"2.45","c":"رَّحِمَ","d":"raḥima","e":"Allah has mercy","i":"رَّحِمَ"},{"b":"1.8","h":"3.96","c":"ٱللَّهُۚ","d":"l-lahu","e":"Allah has mercy","i":"اللّٰهُ​ؕ"},{"b":"4.7","h":"8.25","c":"إِنَّهُۥ","d":"innahu","e":"Indeed, He","i":"اِنَّهٗ"},{"b":"6.6","h":"10.44","c":"هُوَ","d":"huwa","e":"[He]","i":"هُوَ"},{"b":"7.0","h":"11.19","c":"ٱلۡعَزِيزُ","d":"l-ʿazīzu","e":"(is) the All-Mighty","i":"الۡعَزِيۡزُ"},{"b":"8.0","h":"13.29","c":"ٱلرَّحِيمُ","d":"l-raḥīmu","e":"the Most Merciful","i":"الرَّحِيۡمُ"}],"a":{"g":"Except those [believers] on whom Allah has mercy. Indeed, He is the Exalted in Might, the Merciful."}},"43":{"w":[{"b":"0.03","h":"0.35","c":"إِنَّ","d":"inna","e":"Indeed","i":"اِنَّ"},{"b":"1.1","h":"1.78","c":"شَجَرَتَ","d":"shajarata","e":"(the) tree","i":"شَجَرَتَ"},{"b":"2.0","h":"3.37","c":"ٱلزَّقُّومِ","d":"l-zaqūmi","e":"(of) Zaqqum","i":"الزَّقُّوۡمِۙ"}],"a":{"g":"Indeed, the tree of zaqqum"}},"44":{"w":[{"b":"0.11","h":"0.75","c":"طَعَامُ","d":"ṭaʿāmu","e":"(Will be) food","i":"طَعَامُ"},{"b":"0.89","h":"2.41","c":"ٱلۡأَثِيمِ","d":"l-athīmi","e":"(of) the sinner(s)","i":"الۡاَثِيۡمِ ۛۚ   ۖ"}],"a":{"g":"Is food for the sinful."}},"45":{"w":[{"b":"0.03","h":"0.45","c":"كَٱلۡمُهۡلِ","d":"kal-muh'li","e":"Like the murky oil","i":"كَالۡمُهۡلِ ۛۚ"},{"b":"1.0","h":"2.11","c":"يَغۡلِي","d":"yaghlī","e":"it will boil","i":"يَغۡلِىۡ"},{"b":"1.8","h":"3.65","c":"فِي","d":"fī","e":"in","i":"فِى"},{"b":"2.1","h":"4.04","c":"ٱلۡبُطُونِ","d":"l-buṭūni","e":"the bellies","i":"الۡبُطُوۡنِۙ"}],"a":{"g":"Like murky oil, it boils within bellies"}},"46":{"w":[{"b":"0.03","h":"0.45","c":"كَغَلۡيِ","d":"kaghalyi","e":"Like boiling","i":"كَغَلۡىِ"},{"b":"0.86","h":"1.96","c":"ٱلۡحَمِيمِ","d":"l-ḥamīmi","e":"(of) scalding water","i":"الۡحَمِيۡمِ"}],"a":{"g":"Like the boiling of scalding water."}},"47":{"w":[{"b":"0.07","h":"0.03","c":"خُذُوهُ","d":"khudhūhu","e":"Seize him","i":"خُذُوۡهُ"},{"b":"0.91","h":"1.44","c":"فَٱعۡتِلُوهُ","d":"fa-iʿ'tilūhu","e":"and drag him","i":"فَاعۡتِلُوۡهُ"},{"b":"2.3","h":"3.74","c":"إِلَىٰ","d":"ilā","e":"into","i":"اِلٰى"},{"b":"2.7","h":"4.84","c":"سَوَآءِ","d":"sawāi","e":"(the) midst","i":"سَوَآءِ"},{"b":"5.5","h":"7.44","c":"ٱلۡجَحِيمِ","d":"l-jaḥīmi","e":"(of) the Hellfire","i":"الۡجَحِيۡمِ   ۖ"}],"a":{"g":"[It will be commanded], \"Seize him and drag him into the midst of the Hellfire,"}},"48":{"w":[{"b":"0.03","h":"1.2","c":"ثُمَّ","d":"thumma","e":"Then","i":"ثُمَّ"},{"b":"1.3","h":"2.41","c":"صُبُّواْ","d":"ṣubbū","e":"pour","i":"صُبُّوۡا"},{"b":"2.2","h":"4.02","c":"فَوۡقَ","d":"fawqa","e":"over","i":"فَوۡقَ"},{"b":"2.9","h":"5.18","c":"رَأۡسِهِۦ","d":"rasihi","e":"his head","i":"رَاۡسِهٖ"},{"b":"4.0","h":"7.09","c":"مِنۡ","d":"min","e":"of","i":"مِنۡ"},{"b":"4.3","h":"7.65","c":"عَذَابِ","d":"ʿadhābi","e":"(the) punishment","i":"عَذَابِ"},{"b":"5.3","h":"9.29","c":"ٱلۡحَمِيمِ","d":"l-ḥamīmi","e":"(of) the scalding water","i":"الۡحَمِيۡمِؕ"}],"a":{"g":"Then pour over his head from the torment of scalding water.\""}},"49":{"w":[{"b":"0.03","h":"0.93","c":"ذُقۡ","d":"dhuq","e":"Taste!","i":"ذُقۡ ۖۚ"},{"b":"0.49","h":"1.26","c":"إِنَّكَ","d":"innaka","e":"Indeed you","i":"اِنَّكَ"},{"b":"2.1","h":"3.09","c":"أَنتَ","d":"anta","e":"[you] (were)","i":"اَنۡتَ"},{"b":"3.7","h":"4.61","c":"ٱلۡعَزِيزُ","d":"l-ʿazīzu","e":"the mighty","i":"الۡعَزِيۡزُ"},{"b":"4.8","h":"6.59","c":"ٱلۡكَرِيمُ","d":"l-karīmu","e":"the noble","i":"الۡكَرِيۡمُ"}],"a":{"g":"[It will be said], \"Taste! Indeed, you are the honored, the noble!"}},"50":{"w":[{"b":"0.07","h":"0.45","c":"إِنَّ","d":"inna","e":"Indeed","i":"اِنَّ"},{"b":"1.3","h":"1.86","c":"هَٰذَا","d":"hādhā","e":"this","i":"هٰذَا"},{"b":"2.2","h":"3.56","c":"مَا","d":"mā","e":"(is) what","i":"مَا"},{"b":"2.6","h":"4.32","c":"كُنتُم","d":"kuntum","e":"you used (to)","i":"كُنۡتُمۡ"},{"b":"5.0","h":"6.81","c":"بِهِۦ","d":"bihi","e":"[about it]","i":"بِهٖ"},{"b":"5.7","h":"7.97","c":"تَمۡتَرُونَ","d":"tamtarūna","e":"doubt","i":"تَمۡتَرُوۡنَ"}],"a":{"g":"Indeed, this is what you used to dispute.\""}},"51":{"w":[{"b":"0.03","h":"0.8","c":"إِنَّ","d":"inna","e":"Indeed","i":"اِنَّ"},{"b":"1.3","h":"2.37","c":"ٱلۡمُتَّقِينَ","d":"l-mutaqīna","e":"the righteous","i":"الۡمُتَّقِيۡنَ"},{"b":"2.8","h":"4.88","c":"فِي","d":"fī","e":"(will be) in","i":"فِىۡ"},{"b":"3.3","h":"5.79","c":"مَقَامٍ","d":"maqāmin","e":"a place","i":"مَقَامٍ"},{"b":"4.3","h":"7.81","c":"أَمِينٖ","d":"amīnin","e":"secure","i":"اَمِيۡنٍۙ"}],"a":{"g":"Indeed, the righteous will be in a secure place;"}},"52":{"w":[{"b":"0.03","h":"0.65","c":"فِي","d":"fī","e":"In","i":"فِىۡ"},{"b":"0.43","h":"1.22","c":"جَنَّـٰتٖ","d":"jannātin","e":"gardens","i":"جَنّٰتٍ"},{"b":"2.6","h":"4.28","c":"وَعُيُونٖ","d":"waʿuyūnin","e":"and springs","i":"وَّعُيُوۡنٍ ۙ ۚ"}],"a":{"g":"Within gardens and springs,"}},"53":{"w":[{"b":"0.09","h":"0.65","c":"يَلۡبَسُونَ","d":"yalbasūna","e":"Wearing garments","i":"يَّلۡبَسُوۡنَ"},{"b":"1.3","h":"2.63","c":"مِن","d":"min","e":"of","i":"مِنۡ"},{"b":"2.2","h":"3.7","c":"سُندُسٖ","d":"sundusin","e":"fine silk","i":"سُنۡدُسٍ"},{"b":"4.1","h":"6.59","c":"وَإِسۡتَبۡرَقٖ","d":"wa-is'tabraqin","e":"and heavy silk","i":"وَّاِسۡتَبۡرَقٍ"},{"b":"7.1","h":"10.27","c":"مُّتَقَٰبِلِينَ","d":"mutaqābilīna","e":"facing each other","i":"مُّتَقٰبِلِيۡنَۚ ۙ"}],"a":{"g":"Wearing [garments of] fine silk and brocade, facing each other."}},"54":{"w":[{"b":"0.03","h":"0.8","c":"كَذَٰلِكَ","d":"kadhālika","e":"Thus","i":"كَذٰلِكَ"},{"b":"1.1","h":"2.5","c":"وَزَوَّجۡنَٰهُم","d":"wazawwajnāhum","e":"And We will marry them","i":"وَزَوَّجۡنٰهُمۡ"},{"b":"3.9","h":"6.46","c":"بِحُورٍ","d":"biḥūrin","e":"(to) companions with beautiful eyes","i":"بِحُوۡرٍ"},{"b":"4.9","h":"8.45","c":"عِينٖ","d":"ʿīnin","e":"(to) companions with beautiful eyes","i":"عِيۡنٍؕ"}],"a":{"g":"Thus. And We will marry them to fair women with large, [beautiful] eyes."}},"55":{"w":[{"b":"0.06","h":"1.1","c":"يَدۡعُونَ","d":"yadʿūna","e":"They will call","i":"يَدۡعُوۡنَ"},{"b":"1.0","h":"2.78","c":"فِيهَا","d":"fīhā","e":"therein","i":"فِيۡهَا"},{"b":"1.9","h":"4.37","c":"بِكُلِّ","d":"bikulli","e":"for every kind","i":"بِكُلِّ"},{"b":"2.8","h":"5.77","c":"فَٰكِهَةٍ","d":"fākihatin","e":"(of) fruit","i":"فَاكِهَةٍ"},{"b":"4.2","h":"8.42","c":"ءَامِنِينَ","d":"āminīna","e":"secure","i":"اٰمِنِيۡنَۙ"}],"a":{"g":"They will call therein for every [kind of] fruit - safe and secure."}},"56":{"w":[{"b":"0.07","h":"0.6","c":"لَا","d":"lā","e":"Not","i":"لَا"},{"b":"0.45","h":"1.23","c":"يَذُوقُونَ","d":"yadhūqūna","e":"they will taste","i":"يَذُوۡقُوۡنَ"},{"b":"1.8","h":"3.59","c":"فِيهَا","d":"fīhā","e":"therein","i":"فِيۡهَا"},{"b":"2.7","h":"4.92","c":"ٱلۡمَوۡتَ","d":"l-mawta","e":"the death","i":"الۡمَوۡتَ"},{"b":"3.4","h":"6.37","c":"إِلَّا","d":"illā","e":"except","i":"اِلَّا"},{"b":"4.0","h":"7.51","c":"ٱلۡمَوۡتَةَ","d":"l-mawtata","e":"the death","i":"الۡمَوۡتَةَ"},{"b":"5.1","h":"9.36","c":"ٱلۡأُولَىٰۖ","d":"l-ūlā","e":"the first","i":"الۡاُوۡلٰى​ ۚ"},{"b":"6.2","h":"11.39","c":"وَوَقَىٰهُمۡ","d":"wawaqāhum","e":"And He will protect them","i":"وَوَقٰٮهُمۡ"},{"b":"7.5","h":"13.72","c":"عَذَابَ","d":"ʿadhāba","e":"(from the) punishment","i":"عَذَابَ"},{"b":"8.4","h":"15.36","c":"ٱلۡجَحِيمِ","d":"l-jaḥīmi","e":"(of) the Hellfire","i":"الۡجَحِيۡمِۙ"}],"a":{"g":"They will not taste death therein except the first death, and He will have protected them from the punishment of Hellfire"}},"57":{"w":[{"b":"0.03","h":"1.05","c":"فَضۡلٗا","d":"faḍlan","e":"A Bounty","i":"فَضۡلًا"},{"b":"1.7","h":"3.09","c":"مِّن","d":"min","e":"from","i":"مِّنۡ"},{"b":"1.8","h":"3.26","c":"رَّبِّكَۚ","d":"rabbika","e":"your Lord","i":"رَّبِّكَ ​ؕ"},{"b":"3.4","h":"6.9","c":"ذَٰلِكَ","d":"dhālika","e":"That","i":"ذٰ لِكَ"},{"b":"4.2","h":"8.32","c":"هُوَ","d":"huwa","e":"it","i":"هُوَ"},{"b":"4.7","h":"9.15","c":"ٱلۡفَوۡزُ","d":"l-fawzu","e":"(will be) the success","i":"الۡفَوۡزُ"},{"b":"5.6","h":"10.91","c":"ٱلۡعَظِيمُ","d":"l-ʿaẓīmu","e":"the great","i":"الۡعَظِيۡمُ"}],"a":{"g":"As bounty from your Lord. That is what is the great attainment."}},"58":{"w":[{"b":"0.03","h":"0.9","c":"فَإِنَّمَا","d":"fa-innamā","e":"Indeed","i":"فَاِنَّمَا"},{"b":"1.8","h":"3.31","c":"يَسَّرۡنَٰهُ","d":"yassarnāhu","e":"We have made it easy","i":"يَسَّرۡنٰهُ"},{"b":"3.4","h":"6.07","c":"بِلِسَانِكَ","d":"bilisānika","e":"in your tongue","i":"بِلِسَانِكَ"},{"b":"4.7","h":"8.28","c":"لَعَلَّهُمۡ","d":"laʿallahum","e":"so that they may","i":"لَعَلَّهُمۡ"},{"b":"6.0","h":"10.42","c":"يَتَذَكَّرُونَ","d":"yatadhakkarūna","e":"take heed","i":"يَتَذَكَّرُوۡنَ"}],"a":{"g":"And indeed, We have eased the Qur'an in your tongue that they might be reminded."}},"59":{"w":[{"b":"0.03","h":"0.65","c":"فَٱرۡتَقِبۡ","d":"fa-ir'taqib","e":"So watch","i":"فَارۡتَقِبۡ"},{"b":"1.1","h":"2.78","c":"إِنَّهُم","d":"innahum","e":"indeed they","i":"اِنَّهُمۡ"},{"b":"3.7","h":"5.43","c":"مُّرۡتَقِبُونَ","d":"mur'taqibūna","e":"(too are) watching","i":"مُّرۡتَقِبُوۡنَ"}],"a":{"g":"So watch, [O Muhammad]; indeed, they are watching [for your end]."}}}